<BranchesInfo>
<BranchInfo>
<BranchId>AV</BranchId>
<Name>Alta Vista</Name>
<ShortName>Alta Vista</ShortName>
<ImageUrl>
http://biblioottawalibrary.ca/sites/biblioottawalibrary.ca/files/imagecache/branch_image_preview/images/branches/br_al_ext_1.jpg
</ImageUrl>
<BranchHours>
<Hours>
<DayOfWeek>Monday</DayOfWeek>
<Open>10:00</Open>
<Close>20:30</Close>
</Hours>
<Hours>
<DayOfWeek>Tuesday</DayOfWeek>
<Open>10:00</Open>
<Close>20:30</Close>
</Hours>
<Hours>
<DayOfWeek>Wednesday</DayOfWeek>
<Open>10:00</Open>
<Close>20:30</Close>
</Hours>
<Hours>
<DayOfWeek>Thursday</DayOfWeek>
<Open>10:00</Open>
<Close>20:30</Close>
</Hours>
<Hours>
<DayOfWeek>Friday</DayOfWeek>
<Open>13:00</Open>
<Close>18:00</Close>
</Hours>
<Hours>
<DayOfWeek>Saturday</DayOfWeek>
<Open>10:00</Open>
<Close>17:00</Close>
</Hours>
<Hours>
<DayOfWeek>Sunday</DayOfWeek>
<Open>CLOSED</Open>
<Close>CLOSED</Close>
</Hours>
</BranchHours>
<HolidayClosures>
<HolidayClosure>
<HolidayName>New Year's Day</HolidayName>
<HolidayDate>2017-01-01</HolidayDate>
</HolidayClosure>
<HolidayClosure>
<HolidayName>Family Day</HolidayName>
<HolidayDate>2017-02-20</HolidayDate>
</HolidayClosure>
<HolidayClosure>
<HolidayName>Good Friday</HolidayName>
<HolidayDate>2017-04-14</HolidayDate>
</HolidayClosure>
<HolidayClosure>
<HolidayName>Easter Sunday</HolidayName>
<HolidayDate>2017-04-16</HolidayDate>
</HolidayClosure>
<HolidayClosure>
<HolidayName>Easter Monday</HolidayName>
<HolidayDate>2017-04-17</HolidayDate>
</HolidayClosure>
<HolidayClosure>
<HolidayName>Victoria Day</HolidayName>
<HolidayDate>2017-05-22</HolidayDate>
</HolidayClosure>
<HolidayClosure>
<HolidayName>Canada Day</HolidayName>
<HolidayDate>2017-07-01</HolidayDate>
</HolidayClosure>
<HolidayClosure>
<HolidayName>Colonel By Day</HolidayName>
<HolidayDate>2017-08-07</HolidayDate>
</HolidayClosure>
<HolidayClosure>
<HolidayName>Labour Day</HolidayName>
<HolidayDate>2017-09-04</HolidayDate>
</HolidayClosure>
<HolidayClosure>
<HolidayName>Thanksgiving</HolidayName>
<HolidayDate>2017-10-09</HolidayDate>
</HolidayClosure>
<HolidayClosure>
<HolidayName>Remembrance Day</HolidayName>
<HolidayDate>2017-11-11</HolidayDate>
</HolidayClosure>
<HolidayClosure>
<HolidayName>Christmas Eve</HolidayName>
<HolidayDate>2017-12-24</HolidayDate>
</HolidayClosure>
<HolidayClosure>
<HolidayName>Christmas Day</HolidayName>
<HolidayDate>2017-12-25</HolidayDate>
</HolidayClosure>
<HolidayClosure>
<HolidayName>Boxing Day</HolidayName>
<HolidayDate>2017-12-26</HolidayDate>
</HolidayClosure>
<HolidayClosure>
<HolidayName>New Year's Eve</HolidayName>
<HolidayDate>2017-12-31</HolidayDate>
</HolidayClosure>
</HolidayClosures>
<Address>2516 Alta Vista</Address>
<ZipCode>K1V 7T1</ZipCode>
<Coordinates>
<Latitude>45.37831700</Latitude>
<Longitude>-75.66121100</Longitude>
</Coordinates>
<PhoneNumber>613-580-2940</PhoneNumber>
<Email/>
</BranchInfo>
<BranchInfo>
<BranchId>BE</BranchId>
<Name>Beaverbrook</Name>
<ShortName>Beaverbrook</ShortName>
<ImageUrl>
http://biblioottawalibrary.ca/sites/default/files/images/branches/Beaverbrook2014_308x180_0.png
</ImageUrl>
<BranchHours>
<Hours>
<DayOfWeek>Monday</DayOfWeek>
<Open>10:00</Open>
<Close>21:00</Close>
</Hours>
<Hours>
<DayOfWeek>Tuesday</DayOfWeek>
<Open>10:00</Open>
<Close>21:00</Close>
</Hours>
<Hours>
<DayOfWeek>Wednesday</DayOfWeek>
<Open>10:00</Open>
<Close>21:00</Close>
</Hours>
<Hours>
<DayOfWeek>Thursday</DayOfWeek>
<Open>10:00</Open>
<Close>21:00</Close>
</Hours>
<Hours>
<DayOfWeek>Friday</DayOfWeek>
<Open>10:00</Open>
<Close>18:00</Close>
</Hours>
<Hours>
<DayOfWeek>Saturday</DayOfWeek>
<Open>10:00</Open>
<Close>17:00</Close>
</Hours>
<Hours>
<DayOfWeek>Sunday</DayOfWeek>
<Open>CLOSED</Open>
<Close>CLOSED</Close>
</Hours>
</BranchHours>
<HolidayClosures>
<HolidayClosure>
<HolidayName>New Year's Day</HolidayName>
<HolidayDate>2017-01-01</HolidayDate>
</HolidayClosure>
<HolidayClosure>
<HolidayName>Family Day</HolidayName>
<HolidayDate>2017-02-20</HolidayDate>
</HolidayClosure>
<HolidayClosure>
<HolidayName>Good Friday</HolidayName>
<HolidayDate>2017-04-14</HolidayDate>
</HolidayClosure>
<HolidayClosure>
<HolidayName>Easter Sunday</HolidayName>
<HolidayDate>2017-04-16</HolidayDate>
</HolidayClosure>
<HolidayClosure>
<HolidayName>Easter Monday</HolidayName>
<HolidayDate>2017-04-17</HolidayDate>
</HolidayClosure>
<HolidayClosure>
<HolidayName>Victoria Day</HolidayName>
<HolidayDate>2017-05-22</HolidayDate>
</HolidayClosure>
<HolidayClosure>
<HolidayName>Canada Day</HolidayName>
<HolidayDate>2017-07-01</HolidayDate>
</HolidayClosure>
<HolidayClosure>
<HolidayName>Colonel By Day</HolidayName>
<HolidayDate>2017-08-07</HolidayDate>
</HolidayClosure>
<HolidayClosure>
<HolidayName>Labour Day</HolidayName>
<HolidayDate>2017-09-04</HolidayDate>
</HolidayClosure>
<HolidayClosure>
<HolidayName>Thanksgiving</HolidayName>
<HolidayDate>2017-10-09</HolidayDate>
</HolidayClosure>
<HolidayClosure>
<HolidayName>Remembrance Day</HolidayName>
<HolidayDate>2017-11-11</HolidayDate>
</HolidayClosure>
<HolidayClosure>
<HolidayName>Christmas Eve</HolidayName>
<HolidayDate>2017-12-24</HolidayDate>
</HolidayClosure>
<HolidayClosure>
<HolidayName>Christmas Day</HolidayName>
<HolidayDate>2017-12-25</HolidayDate>
</HolidayClosure>
<HolidayClosure>
<HolidayName>Boxing Day</HolidayName>
<HolidayDate>2017-12-26</HolidayDate>
</HolidayClosure>
<HolidayClosure>
<HolidayName>New Year's Eve</HolidayName>
<HolidayDate>2017-12-31</HolidayDate>
</HolidayClosure>
</HolidayClosures>
<Address>2500 Campeau</Address>
<ZipCode>K2K 2W3</ZipCode>
<Coordinates>
<Latitude>45.322052</Latitude>
<Longitude>-75.895177</Longitude>
</Coordinates>
<PhoneNumber>613-580-2940</PhoneNumber>
<Email/>
</BranchInfo>
<BranchInfo>
<BranchId>BH</BranchId>
<Name>Blackburn Hamlet</Name>
<ShortName>Blackburn Hamlet</ShortName>
<ImageUrl>
http://biblioottawalibrary.ca/sites/biblioottawalibrary.ca/files/imagecache/branch_image_preview/images/branches/br_bh_ext_1.jpg
</ImageUrl>
<BranchHours>
<Hours>
<DayOfWeek>Monday</DayOfWeek>
<Open>10:00</Open>
<Close>20:30</Close>
</Hours>
<Hours>
<DayOfWeek>Tuesday</DayOfWeek>
<Open>10:00</Open>
<Close>20:30</Close>
</Hours>
<Hours>
<DayOfWeek>Wednesday</DayOfWeek>
<Open>10:00</Open>
<Close>20:30</Close>
</Hours>
<Hours>
<DayOfWeek>Thursday</DayOfWeek>
<Open>10:00</Open>
<Close>20:30</Close>
</Hours>
<Hours>
<DayOfWeek>Friday</DayOfWeek>
<Open>13:00</Open>
<Close>18:00</Close>
</Hours>
<Hours>
<DayOfWeek>Saturday</DayOfWeek>
<Open>10:00</Open>
<Close>17:00</Close>
</Hours>
<Hours>
<DayOfWeek>Sunday</DayOfWeek>
<Open>CLOSED</Open>
<Close>CLOSED</Close>
</Hours>
</BranchHours>
<HolidayClosures>
<HolidayClosure>
<HolidayName>New Year's Day</HolidayName>
<HolidayDate>2017-01-01</HolidayDate>
</HolidayClosure>
<HolidayClosure>
<HolidayName>Family Day</HolidayName>
<HolidayDate>2017-02-20</HolidayDate>
</HolidayClosure>
<HolidayClosure>
<HolidayName>Good Friday</HolidayName>
<HolidayDate>2017-04-14</HolidayDate>
</HolidayClosure>
<HolidayClosure>
<HolidayName>Easter Sunday</HolidayName>
<HolidayDate>2017-04-16</HolidayDate>
</HolidayClosure>
<HolidayClosure>
<HolidayName>Easter Monday</HolidayName>
<HolidayDate>2017-04-17</HolidayDate>
</HolidayClosure>
<HolidayClosure>
<HolidayName>Victoria Day</HolidayName>
<HolidayDate>2017-05-22</HolidayDate>
</HolidayClosure>
<HolidayClosure>
<HolidayName>Canada Day</HolidayName>
<HolidayDate>2017-07-01</HolidayDate>
</HolidayClosure>
<HolidayClosure>
<HolidayName>Colonel By Day</HolidayName>
<HolidayDate>2017-08-07</HolidayDate>
</HolidayClosure>
<HolidayClosure>
<HolidayName>Labour Day</HolidayName>
<HolidayDate>2017-09-04</HolidayDate>
</HolidayClosure>
<HolidayClosure>
<HolidayName>Thanksgiving</HolidayName>
<HolidayDate>2017-10-09</HolidayDate>
</HolidayClosure>
<HolidayClosure>
<HolidayName>Remembrance Day</HolidayName>
<HolidayDate>2017-11-11</HolidayDate>
</HolidayClosure>
<HolidayClosure>
<HolidayName>Christmas Eve</HolidayName>
<HolidayDate>2017-12-24</HolidayDate>
</HolidayClosure>
<HolidayClosure>
<HolidayName>Christmas Day</HolidayName>
<HolidayDate>2017-12-25</HolidayDate>
</HolidayClosure>
<HolidayClosure>
<HolidayName>Boxing Day</HolidayName>
<HolidayDate>2017-12-26</HolidayDate>
</HolidayClosure>
<HolidayClosure>
<HolidayName>New Year's Eve</HolidayName>
<HolidayDate>2017-12-31</HolidayDate>
</HolidayClosure>
</HolidayClosures>
<Address>199 Glen Park</Address>
<ZipCode>K1B 5B8</ZipCode>
<Coordinates>
<Latitude>45.42970500</Latitude>
<Longitude>-75.56568100</Longitude>
</Coordinates>
<PhoneNumber>613-580-2940</PhoneNumber>
<Email/>
</BranchInfo>
<BranchInfo>
<BranchId>CA</BranchId>
<Name>Carlingwood</Name>
<ShortName>Carlingwood</ShortName>
<ImageUrl>
http://biblioottawalibrary.ca/sites/biblioottawalibrary.ca/files/imagecache/branch_image_preview/images/branches/br_ca_ext_1_0.jpg
</ImageUrl>
<BranchHours>
<Hours>
<DayOfWeek>Monday</DayOfWeek>
<Open>10:00</Open>
<Close>20:30</Close>
</Hours>
<Hours>
<DayOfWeek>Tuesday</DayOfWeek>
<Open>10:00</Open>
<Close>20:30</Close>
</Hours>
<Hours>
<DayOfWeek>Wednesday</DayOfWeek>
<Open>10:00</Open>
<Close>20:30</Close>
</Hours>
<Hours>
<DayOfWeek>Thursday</DayOfWeek>
<Open>10:00</Open>
<Close>20:30</Close>
</Hours>
<Hours>
<DayOfWeek>Friday</DayOfWeek>
<Open>13:00</Open>
<Close>18:00</Close>
</Hours>
<Hours>
<DayOfWeek>Saturday</DayOfWeek>
<Open>10:00</Open>
<Close>17:00</Close>
</Hours>
<Hours>
<DayOfWeek>Sunday</DayOfWeek>
<Open>CLOSED</Open>
<Close>CLOSED</Close>
</Hours>
</BranchHours>
<HolidayClosures>
<HolidayClosure>
<HolidayName>New Year's Day</HolidayName>
<HolidayDate>2017-01-01</HolidayDate>
</HolidayClosure>
<HolidayClosure>
<HolidayName>Family Day</HolidayName>
<HolidayDate>2017-02-20</HolidayDate>
</HolidayClosure>
<HolidayClosure>
<HolidayName>Good Friday</HolidayName>
<HolidayDate>2017-04-14</HolidayDate>
</HolidayClosure>
<HolidayClosure>
<HolidayName>Easter Sunday</HolidayName>
<HolidayDate>2017-04-16</HolidayDate>
</HolidayClosure>
<HolidayClosure>
<HolidayName>Easter Monday</HolidayName>
<HolidayDate>2017-04-17</HolidayDate>
</HolidayClosure>
<HolidayClosure>
<HolidayName>Victoria Day</HolidayName>
<HolidayDate>2017-05-22</HolidayDate>
</HolidayClosure>
<HolidayClosure>
<HolidayName>Canada Day</HolidayName>
<HolidayDate>2017-07-01</HolidayDate>
</HolidayClosure>
<HolidayClosure>
<HolidayName>Colonel By Day</HolidayName>
<HolidayDate>2017-08-07</HolidayDate>
</HolidayClosure>
<HolidayClosure>
<HolidayName>Labour Day</HolidayName>
<HolidayDate>2017-09-04</HolidayDate>
</HolidayClosure>
<HolidayClosure>
<HolidayName>Thanksgiving</HolidayName>
<HolidayDate>2017-10-09</HolidayDate>
</HolidayClosure>
<HolidayClosure>
<HolidayName>Remembrance Day</HolidayName>
<HolidayDate>2017-11-11</HolidayDate>
</HolidayClosure>
<HolidayClosure>
<HolidayName>Christmas Eve</HolidayName>
<HolidayDate>2017-12-24</HolidayDate>
</HolidayClosure>
<HolidayClosure>
<HolidayName>Christmas Day</HolidayName>
<HolidayDate>2017-12-25</HolidayDate>
</HolidayClosure>
<HolidayClosure>
<HolidayName>Boxing Day</HolidayName>
<HolidayDate>2017-12-26</HolidayDate>
</HolidayClosure>
<HolidayClosure>
<HolidayName>New Year's Eve</HolidayName>
<HolidayDate>2017-12-31</HolidayDate>
</HolidayClosure>
</HolidayClosures>
<Address>281 Woodroffe</Address>
<ZipCode>K2A 3W4</ZipCode>
<Coordinates>
<Latitude>45.37367400</Latitude>
<Longitude>-75.77221200</Longitude>
</Coordinates>
<PhoneNumber>613-580-2940</PhoneNumber>
<Email/>
</BranchInfo>
<BranchInfo>
<BranchId>CP</BranchId>
<Name>Carp</Name>
<ShortName>Carp</ShortName>
<ImageUrl>
http://biblioottawalibrary.ca/sites/biblioottawalibrary.ca/files/imagecache/branch_image_preview/images/branches/br_cp_ext_1_0.jpg
</ImageUrl>
<BranchHours>
<Hours>
<DayOfWeek>Monday</DayOfWeek>
<Open>10:00</Open>
<Close>18:00</Close>
</Hours>
<Hours>
<DayOfWeek>Tuesday</DayOfWeek>
<Open>10:00</Open>
<Close>20:30</Close>
</Hours>
<Hours>
<DayOfWeek>Wednesday</DayOfWeek>
<Open>10:00</Open>
<Close>20:30</Close>
</Hours>
<Hours>
<DayOfWeek>Thursday</DayOfWeek>
<Open>10:00</Open>
<Close>20:30</Close>
</Hours>
<Hours>
<DayOfWeek>Friday</DayOfWeek>
<Open>13:00</Open>
<Close>18:00</Close>
</Hours>
<Hours>
<DayOfWeek>Saturday</DayOfWeek>
<Open>10:00</Open>
<Close>17:00</Close>
</Hours>
<Hours>
<DayOfWeek>Sunday</DayOfWeek>
<Open>CLOSED</Open>
<Close>CLOSED</Close>
</Hours>
</BranchHours>
<HolidayClosures>
<HolidayClosure>
<HolidayName>New Year's Day</HolidayName>
<HolidayDate>2017-01-01</HolidayDate>
</HolidayClosure>
<HolidayClosure>
<HolidayName>Family Day</HolidayName>
<HolidayDate>2017-02-20</HolidayDate>
</HolidayClosure>
<HolidayClosure>
<HolidayName>Good Friday</HolidayName>
<HolidayDate>2017-04-14</HolidayDate>
</HolidayClosure>
<HolidayClosure>
<HolidayName>Easter Sunday</HolidayName>
<HolidayDate>2017-04-16</HolidayDate>
</HolidayClosure>
<HolidayClosure>
<HolidayName>Easter Monday</HolidayName>
<HolidayDate>2017-04-17</HolidayDate>
</HolidayClosure>
<HolidayClosure>
<HolidayName>Victoria Day</HolidayName>
<HolidayDate>2017-05-22</HolidayDate>
</HolidayClosure>
<HolidayClosure>
<HolidayName>Canada Day</HolidayName>
<HolidayDate>2017-07-01</HolidayDate>
</HolidayClosure>
<HolidayClosure>
<HolidayName>Colonel By Day</HolidayName>
<HolidayDate>2017-08-07</HolidayDate>
</HolidayClosure>
<HolidayClosure>
<HolidayName>Labour Day</HolidayName>
<HolidayDate>2017-09-04</HolidayDate>
</HolidayClosure>
<HolidayClosure>
<HolidayName>Thanksgiving</HolidayName>
<HolidayDate>2017-10-09</HolidayDate>
</HolidayClosure>
<HolidayClosure>
<HolidayName>Remembrance Day</HolidayName>
<HolidayDate>2017-11-11</HolidayDate>
</HolidayClosure>
<HolidayClosure>
<HolidayName>Christmas Eve</HolidayName>
<HolidayDate>2017-12-24</HolidayDate>
</HolidayClosure>
<HolidayClosure>
<HolidayName>Christmas Day</HolidayName>
<HolidayDate>2017-12-25</HolidayDate>
</HolidayClosure>
<HolidayClosure>
<HolidayName>Boxing Day</HolidayName>
<HolidayDate>2017-12-26</HolidayDate>
</HolidayClosure>
<HolidayClosure>
<HolidayName>New Year's Eve</HolidayName>
<HolidayDate>2017-12-31</HolidayDate>
</HolidayClosure>
</HolidayClosures>
<Address>3911 Carp</Address>
<ZipCode>K0A 1L0</ZipCode>
<Coordinates>
<Latitude>45.35249200</Latitude>
<Longitude>-76.04463800</Longitude>
</Coordinates>
<PhoneNumber>613-580-2940</PhoneNumber>
<Email/>
</BranchInfo>
<BranchInfo>
<BranchId>CE</BranchId>
<Name>Centennial</Name>
<ShortName>Centennial</ShortName>
<ImageUrl>
http://biblioottawalibrary.ca/sites/biblioottawalibrary.ca/files/imagecache/branch_image_preview/images/branches/br_ce_ext_1.jpg
</ImageUrl>
<BranchHours>
<Hours>
<DayOfWeek>Monday</DayOfWeek>
<Open>10:00</Open>
<Close>20:30</Close>
</Hours>
<Hours>
<DayOfWeek>Tuesday</DayOfWeek>
<Open>10:00</Open>
<Close>20:30</Close>
</Hours>
<Hours>
<DayOfWeek>Wednesday</DayOfWeek>
<Open>10:00</Open>
<Close>20:30</Close>
</Hours>
<Hours>
<DayOfWeek>Thursday</DayOfWeek>
<Open>10:00</Open>
<Close>20:30</Close>
</Hours>
<Hours>
<DayOfWeek>Friday</DayOfWeek>
<Open>13:00</Open>
<Close>18:00</Close>
</Hours>
<Hours>
<DayOfWeek>Saturday</DayOfWeek>
<Open>10:00</Open>
<Close>17:00</Close>
</Hours>
<Hours>
<DayOfWeek>Sunday</DayOfWeek>
<Open>CLOSED</Open>
<Close>CLOSED</Close>
</Hours>
</BranchHours>
<HolidayClosures>
<HolidayClosure>
<HolidayName>New Year's Day</HolidayName>
<HolidayDate>2017-01-01</HolidayDate>
</HolidayClosure>
<HolidayClosure>
<HolidayName>Family Day</HolidayName>
<HolidayDate>2017-02-20</HolidayDate>
</HolidayClosure>
<HolidayClosure>
<HolidayName>Good Friday</HolidayName>
<HolidayDate>2017-04-14</HolidayDate>
</HolidayClosure>
<HolidayClosure>
<HolidayName>Easter Sunday</HolidayName>
<HolidayDate>2017-04-16</HolidayDate>
</HolidayClosure>
<HolidayClosure>
<HolidayName>Easter Monday</HolidayName>
<HolidayDate>2017-04-17</HolidayDate>
</HolidayClosure>
<HolidayClosure>
<HolidayName>Victoria Day</HolidayName>
<HolidayDate>2017-05-22</HolidayDate>
</HolidayClosure>
<HolidayClosure>
<HolidayName>Canada Day</HolidayName>
<HolidayDate>2017-07-01</HolidayDate>
</HolidayClosure>
<HolidayClosure>
<HolidayName>Colonel By Day</HolidayName>
<HolidayDate>2017-08-07</HolidayDate>
</HolidayClosure>
<HolidayClosure>
<HolidayName>Labour Day</HolidayName>
<HolidayDate>2017-09-04</HolidayDate>
</HolidayClosure>
<HolidayClosure>
<HolidayName>Thanksgiving</HolidayName>
<HolidayDate>2017-10-09</HolidayDate>
</HolidayClosure>
<HolidayClosure>
<HolidayName>Remembrance Day</HolidayName>
<HolidayDate>2017-11-11</HolidayDate>
</HolidayClosure>
<HolidayClosure>
<HolidayName>Christmas Eve</HolidayName>
<HolidayDate>2017-12-24</HolidayDate>
</HolidayClosure>
<HolidayClosure>
<HolidayName>Christmas Day</HolidayName>
<HolidayDate>2017-12-25</HolidayDate>
</HolidayClosure>
<HolidayClosure>
<HolidayName>Boxing Day</HolidayName>
<HolidayDate>2017-12-26</HolidayDate>
</HolidayClosure>
<HolidayClosure>
<HolidayName>New Year's Eve</HolidayName>
<HolidayDate>2017-12-31</HolidayDate>
</HolidayClosure>
</HolidayClosures>
<Address>3870 Old Richmond Rd.</Address>
<ZipCode>K2H 5C4</ZipCode>
<Coordinates>
<Latitude>45.32148100</Latitude>
<Longitude>-75.82628500</Longitude>
</Coordinates>
<PhoneNumber>613-580-2940</PhoneNumber>
<Email/>
</BranchInfo>
<BranchInfo>
<BranchId>CB</BranchId>
<Name>Constance Bay</Name>
<ShortName>Constance Bay</ShortName>
<ImageUrl>
http://biblioottawalibrary.ca/sites/biblioottawalibrary.ca/files/imagecache/branch_image_preview/images/branches/br_cb_ext_1.jpg
</ImageUrl>
<BranchHours>
<Hours>
<DayOfWeek>Monday</DayOfWeek>
<Open>16:30</Open>
<Close>20:30</Close>
</Hours>
<Hours>
<DayOfWeek>Tuesday</DayOfWeek>
<Open>10:00</Open>
<Close>13:00</Close>
<Open>16:30</Open>
<Close>20:30</Close>
</Hours>
<Hours>
<DayOfWeek>Wednesday</DayOfWeek>
<Open>CLOSED</Open>
<Close>CLOSED</Close>
</Hours>
<Hours>
<DayOfWeek>Thursday</DayOfWeek>
<Open>16:30</Open>
<Close>20:30</Close>
</Hours>
<Hours>
<DayOfWeek>Friday</DayOfWeek>
<Open>CLOSED</Open>
<Close>CLOSED</Close>
</Hours>
<Hours>
<DayOfWeek>Saturday</DayOfWeek>
<Open>10:00</Open>
<Close>14:00</Close>
</Hours>
<Hours>
<DayOfWeek>Sunday</DayOfWeek>
<Open>CLOSED</Open>
<Close>CLOSED</Close>
</Hours>
</BranchHours>
<HolidayClosures>
<HolidayClosure>
<HolidayName>New Year's Day</HolidayName>
<HolidayDate>2017-01-01</HolidayDate>
</HolidayClosure>
<HolidayClosure>
<HolidayName>Family Day</HolidayName>
<HolidayDate>2017-02-20</HolidayDate>
</HolidayClosure>
<HolidayClosure>
<HolidayName>Good Friday</HolidayName>
<HolidayDate>2017-04-14</HolidayDate>
</HolidayClosure>
<HolidayClosure>
<HolidayName>Easter Sunday</HolidayName>
<HolidayDate>2017-04-16</HolidayDate>
</HolidayClosure>
<HolidayClosure>
<HolidayName>Easter Monday</HolidayName>
<HolidayDate>2017-04-17</HolidayDate>
</HolidayClosure>
<HolidayClosure>
<HolidayName>Victoria Day</HolidayName>
<HolidayDate>2017-05-22</HolidayDate>
</HolidayClosure>
<HolidayClosure>
<HolidayName>Canada Day</HolidayName>
<HolidayDate>2017-07-01</HolidayDate>
</HolidayClosure>
<HolidayClosure>
<HolidayName>Colonel By Day</HolidayName>
<HolidayDate>2017-08-07</HolidayDate>
</HolidayClosure>
<HolidayClosure>
<HolidayName>Labour Day</HolidayName>
<HolidayDate>2017-09-04</HolidayDate>
</HolidayClosure>
<HolidayClosure>
<HolidayName>Thanksgiving</HolidayName>
<HolidayDate>2017-10-09</HolidayDate>
</HolidayClosure>
<HolidayClosure>
<HolidayName>Remembrance Day</HolidayName>
<HolidayDate>2017-11-11</HolidayDate>
</HolidayClosure>
<HolidayClosure>
<HolidayName>Christmas Eve</HolidayName>
<HolidayDate>2017-12-24</HolidayDate>
</HolidayClosure>
<HolidayClosure>
<HolidayName>Christmas Day</HolidayName>
<HolidayDate>2017-12-25</HolidayDate>
</HolidayClosure>
<HolidayClosure>
<HolidayName>Boxing Day</HolidayName>
<HolidayDate>2017-12-26</HolidayDate>
</HolidayClosure>
<HolidayClosure>
<HolidayName>New Year's Eve</HolidayName>
<HolidayDate>2017-12-31</HolidayDate>
</HolidayClosure>
</HolidayClosures>
<Address>262 Len Purcell</Address>
<ZipCode>K0A 3M0</ZipCode>
<Coordinates>
<Latitude>45.49804500</Latitude>
<Longitude>-76.09579300</Longitude>
</Coordinates>
<PhoneNumber>613-580-2940</PhoneNumber>
<Email/>
</BranchInfo>
<BranchInfo>
<BranchId>CU</BranchId>
<Name>Cumberland</Name>
<ShortName>Cumberland</ShortName>
<ImageUrl>
http://biblioottawalibrary.ca/sites/biblioottawalibrary.ca/files/imagecache/branch_image_preview/images/branches/br_cu_ext_2_0.jpg
</ImageUrl>
<BranchHours>
<Hours>
<DayOfWeek>Monday</DayOfWeek>
<Open>10:00</Open>
<Close>21:00</Close>
</Hours>
<Hours>
<DayOfWeek>Tuesday</DayOfWeek>
<Open>10:00</Open>
<Close>21:00</Close>
</Hours>
<Hours>
<DayOfWeek>Wednesday</DayOfWeek>
<Open>10:00</Open>
<Close>21:00</Close>
</Hours>
<Hours>
<DayOfWeek>Thursday</DayOfWeek>
<Open>10:00</Open>
<Close>21:00</Close>
</Hours>
<Hours>
<DayOfWeek>Friday</DayOfWeek>
<Open>10:00</Open>
<Close>18:00</Close>
</Hours>
<Hours>
<DayOfWeek>Saturday</DayOfWeek>
<Open>10:00</Open>
<Close>17:00</Close>
</Hours>
<Hours>
<DayOfWeek>Sunday</DayOfWeek>
<Open>CLOSED</Open>
<Close>CLOSED</Close>
</Hours>
</BranchHours>
<HolidayClosures>
<HolidayClosure>
<HolidayName>New Year's Day</HolidayName>
<HolidayDate>2017-01-01</HolidayDate>
</HolidayClosure>
<HolidayClosure>
<HolidayName>Family Day</HolidayName>
<HolidayDate>2017-02-20</HolidayDate>
</HolidayClosure>
<HolidayClosure>
<HolidayName>Good Friday</HolidayName>
<HolidayDate>2017-04-14</HolidayDate>
</HolidayClosure>
<HolidayClosure>
<HolidayName>Easter Sunday</HolidayName>
<HolidayDate>2017-04-16</HolidayDate>
</HolidayClosure>
<HolidayClosure>
<HolidayName>Easter Monday</HolidayName>
<HolidayDate>2017-04-17</HolidayDate>
</HolidayClosure>
<HolidayClosure>
<HolidayName>Victoria Day</HolidayName>
<HolidayDate>2017-05-22</HolidayDate>
</HolidayClosure>
<HolidayClosure>
<HolidayName>Canada Day</HolidayName>
<HolidayDate>2017-07-01</HolidayDate>
</HolidayClosure>
<HolidayClosure>
<HolidayName>Colonel By Day</HolidayName>
<HolidayDate>2017-08-07</HolidayDate>
</HolidayClosure>
<HolidayClosure>
<HolidayName>Labour Day</HolidayName>
<HolidayDate>2017-09-04</HolidayDate>
</HolidayClosure>
<HolidayClosure>
<HolidayName>Thanksgiving</HolidayName>
<HolidayDate>2017-10-09</HolidayDate>
</HolidayClosure>
<HolidayClosure>
<HolidayName>Remembrance Day</HolidayName>
<HolidayDate>2017-11-11</HolidayDate>
</HolidayClosure>
<HolidayClosure>
<HolidayName>Christmas Eve</HolidayName>
<HolidayDate>2017-12-24</HolidayDate>
</HolidayClosure>
<HolidayClosure>
<HolidayName>Christmas Day</HolidayName>
<HolidayDate>2017-12-25</HolidayDate>
</HolidayClosure>
<HolidayClosure>
<HolidayName>Boxing Day</HolidayName>
<HolidayDate>2017-12-26</HolidayDate>
</HolidayClosure>
<HolidayClosure>
<HolidayName>New Year's Eve</HolidayName>
<HolidayDate>2017-12-31</HolidayDate>
</HolidayClosure>
</HolidayClosures>
<Address>1599 Tenth Line</Address>
<ZipCode>K1E 3E8</ZipCode>
<Coordinates>
<Latitude>45.47220000</Latitude>
<Longitude>-75.49367000</Longitude>
</Coordinates>
<PhoneNumber>613-580-2940</PhoneNumber>
<Email/>
</BranchInfo>
<BranchInfo>
<BranchId>EA</BranchId>
<Name>Elmvale Acres</Name>
<ShortName>Elmvale Acres</ShortName>
<ImageUrl>
http://biblioottawalibrary.ca/sites/biblioottawalibrary.ca/files/imagecache/branch_image_preview/images/branches/br_ea_ext_1.jpg
</ImageUrl>
<BranchHours>
<Hours>
<DayOfWeek>Monday</DayOfWeek>
<Open>10:00</Open>
<Close>20:30</Close>
</Hours>
<Hours>
<DayOfWeek>Tuesday</DayOfWeek>
<Open>10:00</Open>
<Close>20:30</Close>
</Hours>
<Hours>
<DayOfWeek>Wednesday</DayOfWeek>
<Open>10:00</Open>
<Close>20:30</Close>
</Hours>
<Hours>
<DayOfWeek>Thursday</DayOfWeek>
<Open>10:00</Open>
<Close>20:30</Close>
</Hours>
<Hours>
<DayOfWeek>Friday</DayOfWeek>
<Open>13:00</Open>
<Close>18:00</Close>
</Hours>
<Hours>
<DayOfWeek>Saturday</DayOfWeek>
<Open>10:00</Open>
<Close>17:00</Close>
</Hours>
<Hours>
<DayOfWeek>Sunday</DayOfWeek>
<Open>CLOSED</Open>
<Close>CLOSED</Close>
</Hours>
</BranchHours>
<HolidayClosures>
<HolidayClosure>
<HolidayName>New Year's Day</HolidayName>
<HolidayDate>2017-01-01</HolidayDate>
</HolidayClosure>
<HolidayClosure>
<HolidayName>Family Day</HolidayName>
<HolidayDate>2017-02-20</HolidayDate>
</HolidayClosure>
<HolidayClosure>
<HolidayName>Good Friday</HolidayName>
<HolidayDate>2017-04-14</HolidayDate>
</HolidayClosure>
<HolidayClosure>
<HolidayName>Easter Sunday</HolidayName>
<HolidayDate>2017-04-16</HolidayDate>
</HolidayClosure>
<HolidayClosure>
<HolidayName>Easter Monday</HolidayName>
<HolidayDate>2017-04-17</HolidayDate>
</HolidayClosure>
<HolidayClosure>
<HolidayName>Victoria Day</HolidayName>
<HolidayDate>2017-05-22</HolidayDate>
</HolidayClosure>
<HolidayClosure>
<HolidayName>Canada Day</HolidayName>
<HolidayDate>2017-07-01</HolidayDate>
</HolidayClosure>
<HolidayClosure>
<HolidayName>Colonel By Day</HolidayName>
<HolidayDate>2017-08-07</HolidayDate>
</HolidayClosure>
<HolidayClosure>
<HolidayName>Labour Day</HolidayName>
<HolidayDate>2017-09-04</HolidayDate>
</HolidayClosure>
<HolidayClosure>
<HolidayName>Thanksgiving</HolidayName>
<HolidayDate>2017-10-09</HolidayDate>
</HolidayClosure>
<HolidayClosure>
<HolidayName>Remembrance Day</HolidayName>
<HolidayDate>2017-11-11</HolidayDate>
</HolidayClosure>
<HolidayClosure>
<HolidayName>Christmas Eve</HolidayName>
<HolidayDate>2017-12-24</HolidayDate>
</HolidayClosure>
<HolidayClosure>
<HolidayName>Christmas Day</HolidayName>
<HolidayDate>2017-12-25</HolidayDate>
</HolidayClosure>
<HolidayClosure>
<HolidayName>Boxing Day</HolidayName>
<HolidayDate>2017-12-26</HolidayDate>
</HolidayClosure>
<HolidayClosure>
<HolidayName>New Year's Eve</HolidayName>
<HolidayDate>2017-12-31</HolidayDate>
</HolidayClosure>
</HolidayClosures>
<Address>1910 St-Laurent</Address>
<ZipCode>K1G 1A4</ZipCode>
<Coordinates>
<Latitude>45.39959500</Latitude>
<Longitude>-75.62312400</Longitude>
</Coordinates>
<PhoneNumber>613-580-2940</PhoneNumber>
<Email/>
</BranchInfo>
<BranchInfo>
<BranchId>EP</BranchId>
<Name>Emerald Plaza</Name>
<ShortName>Emerald Plaza</ShortName>
<ImageUrl>
http://biblioottawalibrary.ca/sites/biblioottawalibrary.ca/files/imagecache/branch_image_preview/images/branches/br_ep_ext_1.jpg
</ImageUrl>
<BranchHours>
<Hours>
<DayOfWeek>Monday</DayOfWeek>
<Open>10:00</Open>
<Close>20:30</Close>
</Hours>
<Hours>
<DayOfWeek>Tuesday</DayOfWeek>
<Open>10:00</Open>
<Close>20:30</Close>
</Hours>
<Hours>
<DayOfWeek>Wednesday</DayOfWeek>
<Open>10:00</Open>
<Close>20:30</Close>
</Hours>
<Hours>
<DayOfWeek>Thursday</DayOfWeek>
<Open>10:00</Open>
<Close>20:30</Close>
</Hours>
<Hours>
<DayOfWeek>Friday</DayOfWeek>
<Open>13:00</Open>
<Close>18:00</Close>
</Hours>
<Hours>
<DayOfWeek>Saturday</DayOfWeek>
<Open>10:00</Open>
<Close>17:00</Close>
</Hours>
<Hours>
<DayOfWeek>Sunday</DayOfWeek>
<Open>CLOSED</Open>
<Close>CLOSED</Close>
</Hours>
</BranchHours>
<HolidayClosures>
<HolidayClosure>
<HolidayName>New Year's Day</HolidayName>
<HolidayDate>2017-01-01</HolidayDate>
</HolidayClosure>
<HolidayClosure>
<HolidayName>Family Day</HolidayName>
<HolidayDate>2017-02-20</HolidayDate>
</HolidayClosure>
<HolidayClosure>
<HolidayName>Good Friday</HolidayName>
<HolidayDate>2017-04-14</HolidayDate>
</HolidayClosure>
<HolidayClosure>
<HolidayName>Easter Sunday</HolidayName>
<HolidayDate>2017-04-16</HolidayDate>
</HolidayClosure>
<HolidayClosure>
<HolidayName>Easter Monday</HolidayName>
<HolidayDate>2017-04-17</HolidayDate>
</HolidayClosure>
<HolidayClosure>
<HolidayName>Victoria Day</HolidayName>
<HolidayDate>2017-05-22</HolidayDate>
</HolidayClosure>
<HolidayClosure>
<HolidayName>Canada Day</HolidayName>
<HolidayDate>2017-07-01</HolidayDate>
</HolidayClosure>
<HolidayClosure>
<HolidayName>Colonel By Day</HolidayName>
<HolidayDate>2017-08-07</HolidayDate>
</HolidayClosure>
<HolidayClosure>
<HolidayName>Labour Day</HolidayName>
<HolidayDate>2017-09-04</HolidayDate>
</HolidayClosure>
<HolidayClosure>
<HolidayName>Thanksgiving</HolidayName>
<HolidayDate>2017-10-09</HolidayDate>
</HolidayClosure>
<HolidayClosure>
<HolidayName>Remembrance Day</HolidayName>
<HolidayDate>2017-11-11</HolidayDate>
</HolidayClosure>
<HolidayClosure>
<HolidayName>Christmas Eve</HolidayName>
<HolidayDate>2017-12-24</HolidayDate>
</HolidayClosure>
<HolidayClosure>
<HolidayName>Christmas Day</HolidayName>
<HolidayDate>2017-12-25</HolidayDate>
</HolidayClosure>
<HolidayClosure>
<HolidayName>Boxing Day</HolidayName>
<HolidayDate>2017-12-26</HolidayDate>
</HolidayClosure>
<HolidayClosure>
<HolidayName>New Year's Eve</HolidayName>
<HolidayDate>2017-12-31</HolidayDate>
</HolidayClosure>
</HolidayClosures>
<Address>1547 Merivale</Address>
<ZipCode>K2G 4V3</ZipCode>
<Coordinates>
<Latitude>45.35532700</Latitude>
<Longitude>-75.73564800</Longitude>
</Coordinates>
<PhoneNumber>613-580-2940</PhoneNumber>
<Email/>
</BranchInfo>
<BranchInfo>
<BranchId>FH</BranchId>
<Name>Fitzroy Harbour</Name>
<ShortName>Fitzroy Harbour</ShortName>
<ImageUrl>
http://biblioottawalibrary.ca/sites/biblioottawalibrary.ca/files/imagecache/branch_image_preview/images/branches/br_fh_ext_1_0.jpg
</ImageUrl>
<BranchHours>
<Hours>
<DayOfWeek>Monday</DayOfWeek>
<Open>17:30</Open>
<Close>20:30</Close>
</Hours>
<Hours>
<DayOfWeek>Tuesday</DayOfWeek>
<Open>CLOSED</Open>
<Close>CLOSED</Close>
</Hours>
<Hours>
<DayOfWeek>Wednesday</DayOfWeek>
<Open>CLOSED</Open>
<Close>CLOSED</Close>
</Hours>
<Hours>
<DayOfWeek>Thursday</DayOfWeek>
<Open>10:00</Open>
<Close>13:00</Close>
<Open>17:30</Open>
<Close>20:30</Close>
</Hours>
<Hours>
<DayOfWeek>Friday</DayOfWeek>
<Open>CLOSED</Open>
<Close>CLOSED</Close>
</Hours>
<Hours>
<DayOfWeek>Saturday</DayOfWeek>
<Open>10:00</Open>
<Close>13:00</Close>
</Hours>
<Hours>
<DayOfWeek>Sunday</DayOfWeek>
<Open>CLOSED</Open>
<Close>CLOSED</Close>
</Hours>
</BranchHours>
<HolidayClosures>
<HolidayClosure>
<HolidayName>New Year's Day</HolidayName>
<HolidayDate>2017-01-01</HolidayDate>
</HolidayClosure>
<HolidayClosure>
<HolidayName>Family Day</HolidayName>
<HolidayDate>2017-02-20</HolidayDate>
</HolidayClosure>
<HolidayClosure>
<HolidayName>Good Friday</HolidayName>
<HolidayDate>2017-04-14</HolidayDate>
</HolidayClosure>
<HolidayClosure>
<HolidayName>Easter Sunday</HolidayName>
<HolidayDate>2017-04-16</HolidayDate>
</HolidayClosure>
<HolidayClosure>
<HolidayName>Easter Monday</HolidayName>
<HolidayDate>2017-04-17</HolidayDate>
</HolidayClosure>
<HolidayClosure>
<HolidayName>Victoria Day</HolidayName>
<HolidayDate>2017-05-22</HolidayDate>
</HolidayClosure>
<HolidayClosure>
<HolidayName>Canada Day</HolidayName>
<HolidayDate>2017-07-01</HolidayDate>
</HolidayClosure>
<HolidayClosure>
<HolidayName>Colonel By Day</HolidayName>
<HolidayDate>2017-08-07</HolidayDate>
</HolidayClosure>
<HolidayClosure>
<HolidayName>Labour Day</HolidayName>
<HolidayDate>2017-09-04</HolidayDate>
</HolidayClosure>
<HolidayClosure>
<HolidayName>Thanksgiving</HolidayName>
<HolidayDate>2017-10-09</HolidayDate>
</HolidayClosure>
<HolidayClosure>
<HolidayName>Remembrance Day</HolidayName>
<HolidayDate>2017-11-11</HolidayDate>
</HolidayClosure>
<HolidayClosure>
<HolidayName>Christmas Eve</HolidayName>
<HolidayDate>2017-12-24</HolidayDate>
</HolidayClosure>
<HolidayClosure>
<HolidayName>Christmas Day</HolidayName>
<HolidayDate>2017-12-25</HolidayDate>
</HolidayClosure>
<HolidayClosure>
<HolidayName>Boxing Day</HolidayName>
<HolidayDate>2017-12-26</HolidayDate>
</HolidayClosure>
<HolidayClosure>
<HolidayName>New Year's Eve</HolidayName>
<HolidayDate>2017-12-31</HolidayDate>
</HolidayClosure>
</HolidayClosures>
<Address>100 Clifford Campbell</Address>
<ZipCode>K0A 1X0</ZipCode>
<Coordinates>
<Latitude>45.47056000</Latitude>
<Longitude>-76.20565700</Longitude>
</Coordinates>
<PhoneNumber>613-580-2940</PhoneNumber>
<Email/>
</BranchInfo>
<BranchInfo>
<BranchId>GR</BranchId>
<Name>Greely</Name>
<ShortName>Greely</ShortName>
<ImageUrl>
http://biblioottawalibrary.ca/sites/biblioottawalibrary.ca/files/imagecache/branch_image_preview/images/branches/br_gr_ext_1.jpg
</ImageUrl>
<BranchHours>
<Hours>
<DayOfWeek>Monday</DayOfWeek>
<Open>10:00</Open>
<Close>13:00</Close>
<Open>16:30</Open>
<Close>20:30</Close>
</Hours>
<Hours>
<DayOfWeek>Tuesday</DayOfWeek>
<Open>10:00</Open>
<Close>13:00</Close>
</Hours>
<Hours>
<DayOfWeek>Wednesday</DayOfWeek>
<Open>10:00</Open>
<Close>13:00</Close>
<Open>16:30</Open>
<Close>20:30</Close>
</Hours>
<Hours>
<DayOfWeek>Thursday</DayOfWeek>
<Open>16:30</Open>
<Close>20:30</Close>
</Hours>
<Hours>
<DayOfWeek>Friday</DayOfWeek>
<Open>CLOSED</Open>
<Close>CLOSED</Close>
</Hours>
<Hours>
<DayOfWeek>Saturday</DayOfWeek>
<Open>10:00</Open>
<Close>14:00</Close>
</Hours>
<Hours>
<DayOfWeek>Sunday</DayOfWeek>
<Open>CLOSED</Open>
<Close>CLOSED</Close>
</Hours>
</BranchHours>
<HolidayClosures>
<HolidayClosure>
<HolidayName>New Year's Day</HolidayName>
<HolidayDate>2017-01-01</HolidayDate>
</HolidayClosure>
<HolidayClosure>
<HolidayName>Family Day</HolidayName>
<HolidayDate>2017-02-20</HolidayDate>
</HolidayClosure>
<HolidayClosure>
<HolidayName>Good Friday</HolidayName>
<HolidayDate>2017-04-14</HolidayDate>
</HolidayClosure>
<HolidayClosure>
<HolidayName>Easter Sunday</HolidayName>
<HolidayDate>2017-04-16</HolidayDate>
</HolidayClosure>
<HolidayClosure>
<HolidayName>Easter Monday</HolidayName>
<HolidayDate>2017-04-17</HolidayDate>
</HolidayClosure>
<HolidayClosure>
<HolidayName>Victoria Day</HolidayName>
<HolidayDate>2017-05-22</HolidayDate>
</HolidayClosure>
<HolidayClosure>
<HolidayName>Canada Day</HolidayName>
<HolidayDate>2017-07-01</HolidayDate>
</HolidayClosure>
<HolidayClosure>
<HolidayName>Colonel By Day</HolidayName>
<HolidayDate>2017-08-07</HolidayDate>
</HolidayClosure>
<HolidayClosure>
<HolidayName>Labour Day</HolidayName>
<HolidayDate>2017-09-04</HolidayDate>
</HolidayClosure>
<HolidayClosure>
<HolidayName>Thanksgiving</HolidayName>
<HolidayDate>2017-10-09</HolidayDate>
</HolidayClosure>
<HolidayClosure>
<HolidayName>Remembrance Day</HolidayName>
<HolidayDate>2017-11-11</HolidayDate>
</HolidayClosure>
<HolidayClosure>
<HolidayName>Christmas Eve</HolidayName>
<HolidayDate>2017-12-24</HolidayDate>
</HolidayClosure>
<HolidayClosure>
<HolidayName>Christmas Day</HolidayName>
<HolidayDate>2017-12-25</HolidayDate>
</HolidayClosure>
<HolidayClosure>
<HolidayName>Boxing Day</HolidayName>
<HolidayDate>2017-12-26</HolidayDate>
</HolidayClosure>
<HolidayClosure>
<HolidayName>New Year's Eve</HolidayName>
<HolidayDate>2017-12-31</HolidayDate>
</HolidayClosure>
</HolidayClosures>
<Address>1448 Meadow Drive</Address>
<ZipCode>K4P 1B1</ZipCode>
<Coordinates>
<Latitude>45.26242000</Latitude>
<Longitude>-75.55672000</Longitude>
</Coordinates>
<PhoneNumber>613-580-2940</PhoneNumber>
<Email/>
</BranchInfo>
<BranchInfo>
<BranchId>GB</BranchId>
<Name>Greenboro</Name>
<ShortName>Greenboro</ShortName>
<ImageUrl>
http://biblioottawalibrary.ca/sites/biblioottawalibrary.ca/files/imagecache/branch_image_preview/images/branches/br_sc_ext_1_0.jpg
</ImageUrl>
<BranchHours>
<Hours>
<DayOfWeek>Monday</DayOfWeek>
<Open>10:00</Open>
<Close>21:00</Close>
</Hours>
<Hours>
<DayOfWeek>Tuesday</DayOfWeek>
<Open>10:00</Open>
<Close>21:00</Close>
</Hours>
<Hours>
<DayOfWeek>Wednesday</DayOfWeek>
<Open>10:00</Open>
<Close>21:00</Close>
</Hours>
<Hours>
<DayOfWeek>Thursday</DayOfWeek>
<Open>10:00</Open>
<Close>21:00</Close>
</Hours>
<Hours>
<DayOfWeek>Friday</DayOfWeek>
<Open>10:00</Open>
<Close>18:00</Close>
</Hours>
<Hours>
<DayOfWeek>Saturday</DayOfWeek>
<Open>10:00</Open>
<Close>17:00</Close>
</Hours>
<Hours>
<DayOfWeek>Sunday</DayOfWeek>
<Open>CLOSED</Open>
<Close>CLOSED</Close>
</Hours>
</BranchHours>
<HolidayClosures>
<HolidayClosure>
<HolidayName>New Year's Day</HolidayName>
<HolidayDate>2017-01-01</HolidayDate>
</HolidayClosure>
<HolidayClosure>
<HolidayName>Family Day</HolidayName>
<HolidayDate>2017-02-20</HolidayDate>
</HolidayClosure>
<HolidayClosure>
<HolidayName>Good Friday</HolidayName>
<HolidayDate>2017-04-14</HolidayDate>
</HolidayClosure>
<HolidayClosure>
<HolidayName>Easter Sunday</HolidayName>
<HolidayDate>2017-04-16</HolidayDate>
</HolidayClosure>
<HolidayClosure>
<HolidayName>Easter Monday</HolidayName>
<HolidayDate>2017-04-17</HolidayDate>
</HolidayClosure>
<HolidayClosure>
<HolidayName>Victoria Day</HolidayName>
<HolidayDate>2017-05-22</HolidayDate>
</HolidayClosure>
<HolidayClosure>
<HolidayName>Canada Day</HolidayName>
<HolidayDate>2017-07-01</HolidayDate>
</HolidayClosure>
<HolidayClosure>
<HolidayName>Colonel By Day</HolidayName>
<HolidayDate>2017-08-07</HolidayDate>
</HolidayClosure>
<HolidayClosure>
<HolidayName>Labour Day</HolidayName>
<HolidayDate>2017-09-04</HolidayDate>
</HolidayClosure>
<HolidayClosure>
<HolidayName>Thanksgiving</HolidayName>
<HolidayDate>2017-10-09</HolidayDate>
</HolidayClosure>
<HolidayClosure>
<HolidayName>Remembrance Day</HolidayName>
<HolidayDate>2017-11-11</HolidayDate>
</HolidayClosure>
<HolidayClosure>
<HolidayName>Christmas Eve</HolidayName>
<HolidayDate>2017-12-24</HolidayDate>
</HolidayClosure>
<HolidayClosure>
<HolidayName>Christmas Day</HolidayName>
<HolidayDate>2017-12-25</HolidayDate>
</HolidayClosure>
<HolidayClosure>
<HolidayName>Boxing Day</HolidayName>
<HolidayDate>2017-12-26</HolidayDate>
</HolidayClosure>
<HolidayClosure>
<HolidayName>New Year's Eve</HolidayName>
<HolidayDate>2017-12-31</HolidayDate>
</HolidayClosure>
</HolidayClosures>
<Address>363 Lorry Greenberg Drive</Address>
<ZipCode>K1T 3P8</ZipCode>
<Coordinates>
<Latitude>45.36387600</Latitude>
<Longitude>-75.63468900</Longitude>
</Coordinates>
<PhoneNumber>613-580-2940</PhoneNumber>
<Email/>
</BranchInfo>
<BranchInfo>
<BranchId>HA</BranchId>
<Name>Hazeldean</Name>
<ShortName>Hazeldean</ShortName>
<ImageUrl>
http://biblioottawalibrary.ca/sites/biblioottawalibrary.ca/files/imagecache/branch_image_preview/images/branches/br_ha_ext_2_0.jpg
</ImageUrl>
<BranchHours>
<Hours>
<DayOfWeek>Monday</DayOfWeek>
<Open>10:00</Open>
<Close>20:30</Close>
</Hours>
<Hours>
<DayOfWeek>Tuesday</DayOfWeek>
<Open>10:00</Open>
<Close>20:30</Close>
</Hours>
<Hours>
<DayOfWeek>Wednesday</DayOfWeek>
<Open>10:00</Open>
<Close>20:30</Close>
</Hours>
<Hours>
<DayOfWeek>Thursday</DayOfWeek>
<Open>10:00</Open>
<Close>20:30</Close>
</Hours>
<Hours>
<DayOfWeek>Friday</DayOfWeek>
<Open>13:00</Open>
<Close>18:00</Close>
</Hours>
<Hours>
<DayOfWeek>Saturday</DayOfWeek>
<Open>10:00</Open>
<Close>17:00</Close>
</Hours>
<Hours>
<DayOfWeek>Sunday</DayOfWeek>
<Open>CLOSED</Open>
<Close>CLOSED</Close>
</Hours>
</BranchHours>
<HolidayClosures>
<HolidayClosure>
<HolidayName>New Year's Day</HolidayName>
<HolidayDate>2017-01-01</HolidayDate>
</HolidayClosure>
<HolidayClosure>
<HolidayName>Family Day</HolidayName>
<HolidayDate>2017-02-20</HolidayDate>
</HolidayClosure>
<HolidayClosure>
<HolidayName>Good Friday</HolidayName>
<HolidayDate>2017-04-14</HolidayDate>
</HolidayClosure>
<HolidayClosure>
<HolidayName>Easter Sunday</HolidayName>
<HolidayDate>2017-04-16</HolidayDate>
</HolidayClosure>
<HolidayClosure>
<HolidayName>Easter Monday</HolidayName>
<HolidayDate>2017-04-17</HolidayDate>
</HolidayClosure>
<HolidayClosure>
<HolidayName>Victoria Day</HolidayName>
<HolidayDate>2017-05-22</HolidayDate>
</HolidayClosure>
<HolidayClosure>
<HolidayName>Canada Day</HolidayName>
<HolidayDate>2017-07-01</HolidayDate>
</HolidayClosure>
<HolidayClosure>
<HolidayName>Colonel By Day</HolidayName>
<HolidayDate>2017-08-07</HolidayDate>
</HolidayClosure>
<HolidayClosure>
<HolidayName>Labour Day</HolidayName>
<HolidayDate>2017-09-04</HolidayDate>
</HolidayClosure>
<HolidayClosure>
<HolidayName>Thanksgiving</HolidayName>
<HolidayDate>2017-10-09</HolidayDate>
</HolidayClosure>
<HolidayClosure>
<HolidayName>Remembrance Day</HolidayName>
<HolidayDate>2017-11-11</HolidayDate>
</HolidayClosure>
<HolidayClosure>
<HolidayName>Christmas Eve</HolidayName>
<HolidayDate>2017-12-24</HolidayDate>
</HolidayClosure>
<HolidayClosure>
<HolidayName>Christmas Day</HolidayName>
<HolidayDate>2017-12-25</HolidayDate>
</HolidayClosure>
<HolidayClosure>
<HolidayName>Boxing Day</HolidayName>
<HolidayDate>2017-12-26</HolidayDate>
</HolidayClosure>
<HolidayClosure>
<HolidayName>New Year's Eve</HolidayName>
<HolidayDate>2017-12-31</HolidayDate>
</HolidayClosure>
</HolidayClosures>
<Address>50 Castlefrank</Address>
<ZipCode>K2L 2N5</ZipCode>
<Coordinates>
<Latitude>45.29557000</Latitude>
<Longitude>-75.88690300</Longitude>
</Coordinates>
<PhoneNumber>613-580-2940</PhoneNumber>
<Email/>
</BranchInfo>
<BranchInfo>
<BranchId>MA</BranchId>
<Name>Main</Name>
<ShortName>Main</ShortName>
<ImageUrl>
http://biblioottawalibrary.ca/sites/biblioottawalibrary.ca/files/imagecache/branch_image_preview/images/branches/br_ma_ext_1_0.jpg
</ImageUrl>
<BranchHours>
<Hours>
<DayOfWeek>Monday</DayOfWeek>
<Open>10:00</Open>
<Close>21:00</Close>
</Hours>
<Hours>
<DayOfWeek>Tuesday</DayOfWeek>
<Open>10:00</Open>
<Close>21:00</Close>
</Hours>
<Hours>
<DayOfWeek>Wednesday</DayOfWeek>
<Open>10:00</Open>
<Close>21:00</Close>
</Hours>
<Hours>
<DayOfWeek>Thursday</DayOfWeek>
<Open>10:00</Open>
<Close>21:00</Close>
</Hours>
<Hours>
<DayOfWeek>Friday</DayOfWeek>
<Open>10:00</Open>
<Close>18:00</Close>
</Hours>
<Hours>
<DayOfWeek>Saturday</DayOfWeek>
<Open>10:00</Open>
<Close>17:00</Close>
</Hours>
<Hours>
<DayOfWeek>Sunday</DayOfWeek>
<Open>CLOSED</Open>
<Close>CLOSED</Close>
</Hours>
</BranchHours>
<HolidayClosures>
<HolidayClosure>
<HolidayName>New Year's Day</HolidayName>
<HolidayDate>2017-01-01</HolidayDate>
</HolidayClosure>
<HolidayClosure>
<HolidayName>Family Day</HolidayName>
<HolidayDate>2017-02-20</HolidayDate>
</HolidayClosure>
<HolidayClosure>
<HolidayName>Good Friday</HolidayName>
<HolidayDate>2017-04-14</HolidayDate>
</HolidayClosure>
<HolidayClosure>
<HolidayName>Easter Sunday</HolidayName>
<HolidayDate>2017-04-16</HolidayDate>
</HolidayClosure>
<HolidayClosure>
<HolidayName>Easter Monday</HolidayName>
<HolidayDate>2017-04-17</HolidayDate>
</HolidayClosure>
<HolidayClosure>
<HolidayName>Victoria Day</HolidayName>
<HolidayDate>2017-05-22</HolidayDate>
</HolidayClosure>
<HolidayClosure>
<HolidayName>Canada Day</HolidayName>
<HolidayDate>2017-07-01</HolidayDate>
</HolidayClosure>
<HolidayClosure>
<HolidayName>Colonel By Day</HolidayName>
<HolidayDate>2017-08-07</HolidayDate>
</HolidayClosure>
<HolidayClosure>
<HolidayName>Labour Day</HolidayName>
<HolidayDate>2017-09-04</HolidayDate>
</HolidayClosure>
<HolidayClosure>
<HolidayName>Thanksgiving</HolidayName>
<HolidayDate>2017-10-09</HolidayDate>
</HolidayClosure>
<HolidayClosure>
<HolidayName>Remembrance Day</HolidayName>
<HolidayDate>2017-11-11</HolidayDate>
</HolidayClosure>
<HolidayClosure>
<HolidayName>Christmas Eve</HolidayName>
<HolidayDate>2017-12-24</HolidayDate>
</HolidayClosure>
<HolidayClosure>
<HolidayName>Christmas Day</HolidayName>
<HolidayDate>2017-12-25</HolidayDate>
</HolidayClosure>
<HolidayClosure>
<HolidayName>Boxing Day</HolidayName>
<HolidayDate>2017-12-26</HolidayDate>
</HolidayClosure>
<HolidayClosure>
<HolidayName>New Year's Eve</HolidayName>
<HolidayDate>2017-12-31</HolidayDate>
</HolidayClosure>
</HolidayClosures>
<Address>120 Metcalfe</Address>
<ZipCode>K1P 5M2</ZipCode>
<Coordinates>
<Latitude>45.42027200</Latitude>
<Longitude>-75.69535600</Longitude>
</Coordinates>
<PhoneNumber>613-580-2940</PhoneNumber>
<Email/>
</BranchInfo>
<BranchInfo>
<BranchId>MK</BranchId>
<Name>Manotick</Name>
<ShortName>Manotick</ShortName>
<ImageUrl>
http://biblioottawalibrary.ca/sites/biblioottawalibrary.ca/files/imagecache/branch_image_preview/images/branches/br_mk_ext_2.jpg
</ImageUrl>
<BranchHours>
<Hours>
<DayOfWeek>Monday</DayOfWeek>
<Open>CLOSED</Open>
<Close>CLOSED</Close>
</Hours>
<Hours>
<DayOfWeek>Tuesday</DayOfWeek>
<Open>10:00</Open>
<Close>20:30</Close>
</Hours>
<Hours>
<DayOfWeek>Wednesday</DayOfWeek>
<Open>10:00</Open>
<Close>20:30</Close>
</Hours>
<Hours>
<DayOfWeek>Thursday</DayOfWeek>
<Open>10:00</Open>
<Close>20:30</Close>
</Hours>
<Hours>
<DayOfWeek>Friday</DayOfWeek>
<Open>13:00</Open>
<Close>18:00</Close>
</Hours>
<Hours>
<DayOfWeek>Saturday</DayOfWeek>
<Open>10:00</Open>
<Close>17:00</Close>
</Hours>
<Hours>
<DayOfWeek>Sunday</DayOfWeek>
<Open>CLOSED</Open>
<Close>CLOSED</Close>
</Hours>
</BranchHours>
<HolidayClosures>
<HolidayClosure>
<HolidayName>New Year's Day</HolidayName>
<HolidayDate>2017-01-01</HolidayDate>
</HolidayClosure>
<HolidayClosure>
<HolidayName>Family Day</HolidayName>
<HolidayDate>2017-02-20</HolidayDate>
</HolidayClosure>
<HolidayClosure>
<HolidayName>Good Friday</HolidayName>
<HolidayDate>2017-04-14</HolidayDate>
</HolidayClosure>
<HolidayClosure>
<HolidayName>Easter Sunday</HolidayName>
<HolidayDate>2017-04-16</HolidayDate>
</HolidayClosure>
<HolidayClosure>
<HolidayName>Easter Monday</HolidayName>
<HolidayDate>2017-04-17</HolidayDate>
</HolidayClosure>
<HolidayClosure>
<HolidayName>Victoria Day</HolidayName>
<HolidayDate>2017-05-22</HolidayDate>
</HolidayClosure>
<HolidayClosure>
<HolidayName>Canada Day</HolidayName>
<HolidayDate>2017-07-01</HolidayDate>
</HolidayClosure>
<HolidayClosure>
<HolidayName>Colonel By Day</HolidayName>
<HolidayDate>2017-08-07</HolidayDate>
</HolidayClosure>
<HolidayClosure>
<HolidayName>Labour Day</HolidayName>
<HolidayDate>2017-09-04</HolidayDate>
</HolidayClosure>
<HolidayClosure>
<HolidayName>Thanksgiving</HolidayName>
<HolidayDate>2017-10-09</HolidayDate>
</HolidayClosure>
<HolidayClosure>
<HolidayName>Remembrance Day</HolidayName>
<HolidayDate>2017-11-11</HolidayDate>
</HolidayClosure>
<HolidayClosure>
<HolidayName>Christmas Eve</HolidayName>
<HolidayDate>2017-12-24</HolidayDate>
</HolidayClosure>
<HolidayClosure>
<HolidayName>Christmas Day</HolidayName>
<HolidayDate>2017-12-25</HolidayDate>
</HolidayClosure>
<HolidayClosure>
<HolidayName>Boxing Day</HolidayName>
<HolidayDate>2017-12-26</HolidayDate>
</HolidayClosure>
<HolidayClosure>
<HolidayName>New Year's Eve</HolidayName>
<HolidayDate>2017-12-31</HolidayDate>
</HolidayClosure>
</HolidayClosures>
<Address>5499 South River</Address>
<ZipCode>K2G 4V3</ZipCode>
<Coordinates>
<Latitude>45.23071700</Latitude>
<Longitude>-75.67878500</Longitude>
</Coordinates>
<PhoneNumber>613-580-2940</PhoneNumber>
<Email/>
</BranchInfo>
<BranchInfo>
<BranchId>ME</BranchId>
<Name>Metcalfe</Name>
<ShortName>Metcalfe</ShortName>
<ImageUrl>
http://biblioottawalibrary.ca/sites/biblioottawalibrary.ca/files/imagecache/branch_image_preview/images/branches/br_me_ext_1_0.jpg
</ImageUrl>
<BranchHours>
<Hours>
<DayOfWeek>Monday</DayOfWeek>
<Open>17:30</Open>
<Close>20:30</Close>
</Hours>
<Hours>
<DayOfWeek>Tuesday</DayOfWeek>
<Open>10:00</Open>
<Close>13:00</Close>
<Open>17:30</Open>
<Close>20:30</Close>
</Hours>
<Hours>
<DayOfWeek>Wednesday</DayOfWeek>
<Open>16:30</Open>
<Close>20:30</Close>
</Hours>
<Hours>
<DayOfWeek>Thursday</DayOfWeek>
<Open>10:00</Open>
<Close>13:00</Close>
<Open>17:30</Open>
<Close>20:30</Close>
</Hours>
<Hours>
<DayOfWeek>Friday</DayOfWeek>
<Open>CLOSED</Open>
<Close>CLOSED</Close>
</Hours>
<Hours>
<DayOfWeek>Saturday</DayOfWeek>
<Open>10:00</Open>
<Close>14:00</Close>
</Hours>
<Hours>
<DayOfWeek>Sunday</DayOfWeek>
<Open>CLOSED</Open>
<Close>CLOSED</Close>
</Hours>
</BranchHours>
<HolidayClosures>
<HolidayClosure>
<HolidayName>New Year's Day</HolidayName>
<HolidayDate>2017-01-01</HolidayDate>
</HolidayClosure>
<HolidayClosure>
<HolidayName>Family Day</HolidayName>
<HolidayDate>2017-02-20</HolidayDate>
</HolidayClosure>
<HolidayClosure>
<HolidayName>Good Friday</HolidayName>
<HolidayDate>2017-04-14</HolidayDate>
</HolidayClosure>
<HolidayClosure>
<HolidayName>Easter Sunday</HolidayName>
<HolidayDate>2017-04-16</HolidayDate>
</HolidayClosure>
<HolidayClosure>
<HolidayName>Easter Monday</HolidayName>
<HolidayDate>2017-04-17</HolidayDate>
</HolidayClosure>
<HolidayClosure>
<HolidayName>Victoria Day</HolidayName>
<HolidayDate>2017-05-22</HolidayDate>
</HolidayClosure>
<HolidayClosure>
<HolidayName>Canada Day</HolidayName>
<HolidayDate>2017-07-01</HolidayDate>
</HolidayClosure>
<HolidayClosure>
<HolidayName>Colonel By Day</HolidayName>
<HolidayDate>2017-08-07</HolidayDate>
</HolidayClosure>
<HolidayClosure>
<HolidayName>Labour Day</HolidayName>
<HolidayDate>2017-09-04</HolidayDate>
</HolidayClosure>
<HolidayClosure>
<HolidayName>Thanksgiving</HolidayName>
<HolidayDate>2017-10-09</HolidayDate>
</HolidayClosure>
<HolidayClosure>
<HolidayName>Remembrance Day</HolidayName>
<HolidayDate>2017-11-11</HolidayDate>
</HolidayClosure>
<HolidayClosure>
<HolidayName>Christmas Eve</HolidayName>
<HolidayDate>2017-12-24</HolidayDate>
</HolidayClosure>
<HolidayClosure>
<HolidayName>Christmas Day</HolidayName>
<HolidayDate>2017-12-25</HolidayDate>
</HolidayClosure>
<HolidayClosure>
<HolidayName>Boxing Day</HolidayName>
<HolidayDate>2017-12-26</HolidayDate>
</HolidayClosure>
<HolidayClosure>
<HolidayName>New Year's Eve</HolidayName>
<HolidayDate>2017-12-31</HolidayDate>
</HolidayClosure>
</HolidayClosures>
<Address>2782 8th Line</Address>
<ZipCode>K0A 2P0</ZipCode>
<Coordinates>
<Latitude>45.23068700</Latitude>
<Longitude>-75.46946500</Longitude>
</Coordinates>
<PhoneNumber>613-580-2940</PhoneNumber>
<Email/>
</BranchInfo>
<BranchInfo>
<BranchId>MU</BranchId>
<Name>Munster</Name>
<ShortName>Munster</ShortName>
<ImageUrl>
http://biblioottawalibrary.ca/sites/biblioottawalibrary.ca/files/imagecache/branch_image_preview/images/branches/br_mu_ext_1_0.jpg
</ImageUrl>
<BranchHours>
<Hours>
<DayOfWeek>Monday</DayOfWeek>
<Open>14:30</Open>
<Close>17:30</Close>
<Open>18:30</Open>
<Close>20:30</Close>
</Hours>
<Hours>
<DayOfWeek>Tuesday</DayOfWeek>
<Open>14:30</Open>
<Close>17:30</Close>
<Open>18:30</Open>
<Close>20:30</Close>
</Hours>
<Hours>
<DayOfWeek>Wednesday</DayOfWeek>
<Open>14:30</Open>
<Close>17:30</Close>
<Open>18:30</Open>
<Close>20:30</Close>
</Hours>
<Hours>
<DayOfWeek>Thursday</DayOfWeek>
<Open>14:30</Open>
<Close>17:30</Close>
<Open>18:30</Open>
<Close>20:30</Close>
</Hours>
<Hours>
<DayOfWeek>Friday</DayOfWeek>
<Open>CLOSED</Open>
<Close>CLOSED</Close>
</Hours>
<Hours>
<DayOfWeek>Saturday</DayOfWeek>
<Open>10:00</Open>
<Close>14:00</Close>
</Hours>
<Hours>
<DayOfWeek>Sunday</DayOfWeek>
<Open>CLOSED</Open>
<Close>CLOSED</Close>
</Hours>
</BranchHours>
<HolidayClosures>
<HolidayClosure>
<HolidayName>New Year's Day</HolidayName>
<HolidayDate>2017-01-01</HolidayDate>
</HolidayClosure>
<HolidayClosure>
<HolidayName>Family Day</HolidayName>
<HolidayDate>2017-02-20</HolidayDate>
</HolidayClosure>
<HolidayClosure>
<HolidayName>Good Friday</HolidayName>
<HolidayDate>2017-04-14</HolidayDate>
</HolidayClosure>
<HolidayClosure>
<HolidayName>Easter Sunday</HolidayName>
<HolidayDate>2017-04-16</HolidayDate>
</HolidayClosure>
<HolidayClosure>
<HolidayName>Easter Monday</HolidayName>
<HolidayDate>2017-04-17</HolidayDate>
</HolidayClosure>
<HolidayClosure>
<HolidayName>Victoria Day</HolidayName>
<HolidayDate>2017-05-22</HolidayDate>
</HolidayClosure>
<HolidayClosure>
<HolidayName>Canada Day</HolidayName>
<HolidayDate>2017-07-01</HolidayDate>
</HolidayClosure>
<HolidayClosure>
<HolidayName>Colonel By Day</HolidayName>
<HolidayDate>2017-08-07</HolidayDate>
</HolidayClosure>
<HolidayClosure>
<HolidayName>Labour Day</HolidayName>
<HolidayDate>2017-09-04</HolidayDate>
</HolidayClosure>
<HolidayClosure>
<HolidayName>Thanksgiving</HolidayName>
<HolidayDate>2017-10-09</HolidayDate>
</HolidayClosure>
<HolidayClosure>
<HolidayName>Remembrance Day</HolidayName>
<HolidayDate>2017-11-11</HolidayDate>
</HolidayClosure>
<HolidayClosure>
<HolidayName>Christmas Eve</HolidayName>
<HolidayDate>2017-12-24</HolidayDate>
</HolidayClosure>
<HolidayClosure>
<HolidayName>Christmas Day</HolidayName>
<HolidayDate>2017-12-25</HolidayDate>
</HolidayClosure>
<HolidayClosure>
<HolidayName>Boxing Day</HolidayName>
<HolidayDate>2017-12-26</HolidayDate>
</HolidayClosure>
<HolidayClosure>
<HolidayName>New Year's Eve</HolidayName>
<HolidayDate>2017-12-31</HolidayDate>
</HolidayClosure>
</HolidayClosures>
<Address>7749 Bleeks</Address>
<ZipCode>K0A 2P0</ZipCode>
<Coordinates>
<Latitude>45.16630500</Latitude>
<Longitude>-75.93902300</Longitude>
</Coordinates>
<PhoneNumber>613-580-2940</PhoneNumber>
<Email/>
</BranchInfo>
<BranchInfo>
<BranchId>NC</BranchId>
<Name>Nepean Centrepointe</Name>
<ShortName>Nepean Centrepointe</ShortName>
<ImageUrl>
http://biblioottawalibrary.ca/sites/biblioottawalibrary.ca/files/imagecache/branch_image_preview/images/branches/br_nc_ext_1.jpg
</ImageUrl>
<BranchHours>
<Hours>
<DayOfWeek>Monday</DayOfWeek>
<Open>10:00</Open>
<Close>21:00</Close>
</Hours>
<Hours>
<DayOfWeek>Tuesday</DayOfWeek>
<Open>10:00</Open>
<Close>21:00</Close>
</Hours>
<Hours>
<DayOfWeek>Wednesday</DayOfWeek>
<Open>10:00</Open>
<Close>21:00</Close>
</Hours>
<Hours>
<DayOfWeek>Thursday</DayOfWeek>
<Open>10:00</Open>
<Close>21:00</Close>
</Hours>
<Hours>
<DayOfWeek>Friday</DayOfWeek>
<Open>10:00</Open>
<Close>18:00</Close>
</Hours>
<Hours>
<DayOfWeek>Saturday</DayOfWeek>
<Open>10:00</Open>
<Close>17:00</Close>
</Hours>
<Hours>
<DayOfWeek>Sunday</DayOfWeek>
<Open>CLOSED</Open>
<Close>CLOSED</Close>
</Hours>
</BranchHours>
<HolidayClosures>
<HolidayClosure>
<HolidayName>New Year's Day</HolidayName>
<HolidayDate>2017-01-01</HolidayDate>
</HolidayClosure>
<HolidayClosure>
<HolidayName>Family Day</HolidayName>
<HolidayDate>2017-02-20</HolidayDate>
</HolidayClosure>
<HolidayClosure>
<HolidayName>Good Friday</HolidayName>
<HolidayDate>2017-04-14</HolidayDate>
</HolidayClosure>
<HolidayClosure>
<HolidayName>Easter Sunday</HolidayName>
<HolidayDate>2017-04-16</HolidayDate>
</HolidayClosure>
<HolidayClosure>
<HolidayName>Easter Monday</HolidayName>
<HolidayDate>2017-04-17</HolidayDate>
</HolidayClosure>
<HolidayClosure>
<HolidayName>Victoria Day</HolidayName>
<HolidayDate>2017-05-22</HolidayDate>
</HolidayClosure>
<HolidayClosure>
<HolidayName>Canada Day</HolidayName>
<HolidayDate>2017-07-01</HolidayDate>
</HolidayClosure>
<HolidayClosure>
<HolidayName>Colonel By Day</HolidayName>
<HolidayDate>2017-08-07</HolidayDate>
</HolidayClosure>
<HolidayClosure>
<HolidayName>Labour Day</HolidayName>
<HolidayDate>2017-09-04</HolidayDate>
</HolidayClosure>
<HolidayClosure>
<HolidayName>Thanksgiving</HolidayName>
<HolidayDate>2017-10-09</HolidayDate>
</HolidayClosure>
<HolidayClosure>
<HolidayName>Remembrance Day</HolidayName>
<HolidayDate>2017-11-11</HolidayDate>
</HolidayClosure>
<HolidayClosure>
<HolidayName>Christmas Eve</HolidayName>
<HolidayDate>2017-12-24</HolidayDate>
</HolidayClosure>
<HolidayClosure>
<HolidayName>Christmas Day</HolidayName>
<HolidayDate>2017-12-25</HolidayDate>
</HolidayClosure>
<HolidayClosure>
<HolidayName>Boxing Day</HolidayName>
<HolidayDate>2017-12-26</HolidayDate>
</HolidayClosure>
<HolidayClosure>
<HolidayName>New Year's Eve</HolidayName>
<HolidayDate>2017-12-31</HolidayDate>
</HolidayClosure>
</HolidayClosures>
<Address>101 Centrepointe</Address>
<ZipCode>K2G 5K7</ZipCode>
<Coordinates>
<Latitude>45.34591700</Latitude>
<Longitude>-75.76208400</Longitude>
</Coordinates>
<PhoneNumber>613-580-2940</PhoneNumber>
<Email/>
</BranchInfo>
<BranchInfo>
<BranchId>NG</BranchId>
<Name>North Gloucester</Name>
<ShortName>North Gloucester</ShortName>
<ImageUrl>
http://biblioottawalibrary.ca/sites/biblioottawalibrary.ca/files/imagecache/branch_image_preview/images/branches/br_ng_ext_1_0.jpg
</ImageUrl>
<BranchHours>
<Hours>
<DayOfWeek>Monday</DayOfWeek>
<Open>10:00</Open>
<Close>20:30</Close>
</Hours>
<Hours>
<DayOfWeek>Tuesday</DayOfWeek>
<Open>10:00</Open>
<Close>20:30</Close>
</Hours>
<Hours>
<DayOfWeek>Wednesday</DayOfWeek>
<Open>10:00</Open>
<Close>20:30</Close>
</Hours>
<Hours>
<DayOfWeek>Thursday</DayOfWeek>
<Open>10:00</Open>
<Close>20:30</Close>
</Hours>
<Hours>
<DayOfWeek>Friday</DayOfWeek>
<Open>13:00</Open>
<Close>18:00</Close>
</Hours>
<Hours>
<DayOfWeek>Saturday</DayOfWeek>
<Open>10:00</Open>
<Close>17:00</Close>
</Hours>
<Hours>
<DayOfWeek>Sunday</DayOfWeek>
<Open>CLOSED</Open>
<Close>CLOSED</Close>
</Hours>
</BranchHours>
<HolidayClosures>
<HolidayClosure>
<HolidayName>New Year's Day</HolidayName>
<HolidayDate>2017-01-01</HolidayDate>
</HolidayClosure>
<HolidayClosure>
<HolidayName>Family Day</HolidayName>
<HolidayDate>2017-02-20</HolidayDate>
</HolidayClosure>
<HolidayClosure>
<HolidayName>Good Friday</HolidayName>
<HolidayDate>2017-04-14</HolidayDate>
</HolidayClosure>
<HolidayClosure>
<HolidayName>Easter Sunday</HolidayName>
<HolidayDate>2017-04-16</HolidayDate>
</HolidayClosure>
<HolidayClosure>
<HolidayName>Easter Monday</HolidayName>
<HolidayDate>2017-04-17</HolidayDate>
</HolidayClosure>
<HolidayClosure>
<HolidayName>Victoria Day</HolidayName>
<HolidayDate>2017-05-22</HolidayDate>
</HolidayClosure>
<HolidayClosure>
<HolidayName>Canada Day</HolidayName>
<HolidayDate>2017-07-01</HolidayDate>
</HolidayClosure>
<HolidayClosure>
<HolidayName>Colonel By Day</HolidayName>
<HolidayDate>2017-08-07</HolidayDate>
</HolidayClosure>
<HolidayClosure>
<HolidayName>Labour Day</HolidayName>
<HolidayDate>2017-09-04</HolidayDate>
</HolidayClosure>
<HolidayClosure>
<HolidayName>Thanksgiving</HolidayName>
<HolidayDate>2017-10-09</HolidayDate>
</HolidayClosure>
<HolidayClosure>
<HolidayName>Remembrance Day</HolidayName>
<HolidayDate>2017-11-11</HolidayDate>
</HolidayClosure>
<HolidayClosure>
<HolidayName>Christmas Eve</HolidayName>
<HolidayDate>2017-12-24</HolidayDate>
</HolidayClosure>
<HolidayClosure>
<HolidayName>Christmas Day</HolidayName>
<HolidayDate>2017-12-25</HolidayDate>
</HolidayClosure>
<HolidayClosure>
<HolidayName>Boxing Day</HolidayName>
<HolidayDate>2017-12-26</HolidayDate>
</HolidayClosure>
<HolidayClosure>
<HolidayName>New Year's Eve</HolidayName>
<HolidayDate>2017-12-31</HolidayDate>
</HolidayClosure>
</HolidayClosures>
<Address>2036 Ogilvie</Address>
<ZipCode>K1J 7N8</ZipCode>
<Coordinates>
<Latitude>45.43947800</Latitude>
<Longitude>-75.60140800</Longitude>
</Coordinates>
<PhoneNumber>613-580-2940</PhoneNumber>
<Email/>
</BranchInfo>
<BranchInfo>
<BranchId>GO</BranchId>
<Name>North Gower</Name>
<ShortName>North Gower</ShortName>
<ImageUrl>
http://biblioottawalibrary.ca/sites/biblioottawalibrary.ca/files/imagecache/branch_image_preview/images/branches/br_go_ext_1_0.jpg
</ImageUrl>
<BranchHours>
<Hours>
<DayOfWeek>Monday</DayOfWeek>
<Open>17:00</Open>
<Close>20:30</Close>
</Hours>
<Hours>
<DayOfWeek>Tuesday</DayOfWeek>
<Open>10:00</Open>
<Close>20:30</Close>
</Hours>
<Hours>
<DayOfWeek>Wednesday</DayOfWeek>
<Open>10:00</Open>
<Close>12:30</Close>
<Open>13:00</Open>
<Close>17:00</Close>
</Hours>
<Hours>
<DayOfWeek>Thursday</DayOfWeek>
<Open>13:00</Open>
<Close>20:30</Close>
</Hours>
<Hours>
<DayOfWeek>Friday</DayOfWeek>
<Open>CLOSED</Open>
<Close>CLOSED</Close>
</Hours>
<Hours>
<DayOfWeek>Saturday</DayOfWeek>
<Open>10:00</Open>
<Close>14:00</Close>
</Hours>
<Hours>
<DayOfWeek>Sunday</DayOfWeek>
<Open>CLOSED</Open>
<Close>CLOSED</Close>
</Hours>
</BranchHours>
<HolidayClosures>
<HolidayClosure>
<HolidayName>New Year's Day</HolidayName>
<HolidayDate>2017-01-01</HolidayDate>
</HolidayClosure>
<HolidayClosure>
<HolidayName>Family Day</HolidayName>
<HolidayDate>2017-02-20</HolidayDate>
</HolidayClosure>
<HolidayClosure>
<HolidayName>Good Friday</HolidayName>
<HolidayDate>2017-04-14</HolidayDate>
</HolidayClosure>
<HolidayClosure>
<HolidayName>Easter Sunday</HolidayName>
<HolidayDate>2017-04-16</HolidayDate>
</HolidayClosure>
<HolidayClosure>
<HolidayName>Easter Monday</HolidayName>
<HolidayDate>2017-04-17</HolidayDate>
</HolidayClosure>
<HolidayClosure>
<HolidayName>Victoria Day</HolidayName>
<HolidayDate>2017-05-22</HolidayDate>
</HolidayClosure>
<HolidayClosure>
<HolidayName>Canada Day</HolidayName>
<HolidayDate>2017-07-01</HolidayDate>
</HolidayClosure>
<HolidayClosure>
<HolidayName>Colonel By Day</HolidayName>
<HolidayDate>2017-08-07</HolidayDate>
</HolidayClosure>
<HolidayClosure>
<HolidayName>Labour Day</HolidayName>
<HolidayDate>2017-09-04</HolidayDate>
</HolidayClosure>
<HolidayClosure>
<HolidayName>Thanksgiving</HolidayName>
<HolidayDate>2017-10-09</HolidayDate>
</HolidayClosure>
<HolidayClosure>
<HolidayName>Remembrance Day</HolidayName>
<HolidayDate>2017-11-11</HolidayDate>
</HolidayClosure>
<HolidayClosure>
<HolidayName>Christmas Eve</HolidayName>
<HolidayDate>2017-12-24</HolidayDate>
</HolidayClosure>
<HolidayClosure>
<HolidayName>Christmas Day</HolidayName>
<HolidayDate>2017-12-25</HolidayDate>
</HolidayClosure>
<HolidayClosure>
<HolidayName>Boxing Day</HolidayName>
<HolidayDate>2017-12-26</HolidayDate>
</HolidayClosure>
<HolidayClosure>
<HolidayName>New Year's Eve</HolidayName>
<HolidayDate>2017-12-31</HolidayDate>
</HolidayClosure>
</HolidayClosures>
<Address>6579 Fourth Line</Address>
<ZipCode>K0A 2T0</ZipCode>
<Coordinates>
<Latitude>45.13396600</Latitude>
<Longitude>-75.71768800</Longitude>
</Coordinates>
<PhoneNumber>613-580-2940</PhoneNumber>
<Email/>
</BranchInfo>
<BranchInfo>
<BranchId>OR</BranchId>
<Name>Orlans</Name>
<ShortName>Orlans</ShortName>
<ImageUrl>
http://biblioottawalibrary.ca/sites/biblioottawalibrary.ca/files/imagecache/branch_image_preview/images/branches/br_or_ext_1.jpg
</ImageUrl>
<BranchHours>
<Hours>
<DayOfWeek>Monday</DayOfWeek>
<Open>10:00</Open>
<Close>20:30</Close>
</Hours>
<Hours>
<DayOfWeek>Tuesday</DayOfWeek>
<Open>10:00</Open>
<Close>20:30</Close>
</Hours>
<Hours>
<DayOfWeek>Wednesday</DayOfWeek>
<Open>10:00</Open>
<Close>20:30</Close>
</Hours>
<Hours>
<DayOfWeek>Thursday</DayOfWeek>
<Open>10:00</Open>
<Close>20:30</Close>
</Hours>
<Hours>
<DayOfWeek>Friday</DayOfWeek>
<Open>13:00</Open>
<Close>18:00</Close>
</Hours>
<Hours>
<DayOfWeek>Saturday</DayOfWeek>
<Open>10:00</Open>
<Close>17:00</Close>
</Hours>
<Hours>
<DayOfWeek>Sunday</DayOfWeek>
<Open>CLOSED</Open>
<Close>CLOSED</Close>
</Hours>
</BranchHours>
<HolidayClosures>
<HolidayClosure>
<HolidayName>New Year's Day</HolidayName>
<HolidayDate>2017-01-01</HolidayDate>
</HolidayClosure>
<HolidayClosure>
<HolidayName>Family Day</HolidayName>
<HolidayDate>2017-02-20</HolidayDate>
</HolidayClosure>
<HolidayClosure>
<HolidayName>Good Friday</HolidayName>
<HolidayDate>2017-04-14</HolidayDate>
</HolidayClosure>
<HolidayClosure>
<HolidayName>Easter Sunday</HolidayName>
<HolidayDate>2017-04-16</HolidayDate>
</HolidayClosure>
<HolidayClosure>
<HolidayName>Easter Monday</HolidayName>
<HolidayDate>2017-04-17</HolidayDate>
</HolidayClosure>
<HolidayClosure>
<HolidayName>Victoria Day</HolidayName>
<HolidayDate>2017-05-22</HolidayDate>
</HolidayClosure>
<HolidayClosure>
<HolidayName>Canada Day</HolidayName>
<HolidayDate>2017-07-01</HolidayDate>
</HolidayClosure>
<HolidayClosure>
<HolidayName>Colonel By Day</HolidayName>
<HolidayDate>2017-08-07</HolidayDate>
</HolidayClosure>
<HolidayClosure>
<HolidayName>Labour Day</HolidayName>
<HolidayDate>2017-09-04</HolidayDate>
</HolidayClosure>
<HolidayClosure>
<HolidayName>Thanksgiving</HolidayName>
<HolidayDate>2017-10-09</HolidayDate>
</HolidayClosure>
<HolidayClosure>
<HolidayName>Remembrance Day</HolidayName>
<HolidayDate>2017-11-11</HolidayDate>
</HolidayClosure>
<HolidayClosure>
<HolidayName>Christmas Eve</HolidayName>
<HolidayDate>2017-12-24</HolidayDate>
</HolidayClosure>
<HolidayClosure>
<HolidayName>Christmas Day</HolidayName>
<HolidayDate>2017-12-25</HolidayDate>
</HolidayClosure>
<HolidayClosure>
<HolidayName>Boxing Day</HolidayName>
<HolidayDate>2017-12-26</HolidayDate>
</HolidayClosure>
<HolidayClosure>
<HolidayName>New Year's Eve</HolidayName>
<HolidayDate>2017-12-31</HolidayDate>
</HolidayClosure>
</HolidayClosures>
<Address>1705 Orlans</Address>
<ZipCode>K1C 4W2</ZipCode>
<Coordinates>
<Latitude>45.45733100</Latitude>
<Longitude>-75.52486900</Longitude>
</Coordinates>
<PhoneNumber>613-580-2940</PhoneNumber>
<Email/>
</BranchInfo>
<BranchInfo>
<BranchId>OS</BranchId>
<Name>Osgoode</Name>
<ShortName>Osgoode</ShortName>
<ImageUrl>
http://biblioottawalibrary.ca/sites/biblioottawalibrary.ca/files/imagecache/branch_image_preview/images/branches/br_os_ext_1_0.jpg
</ImageUrl>
<BranchHours>
<Hours>
<DayOfWeek>Monday</DayOfWeek>
<Open>10:00</Open>
<Close>13:00</Close>
<Open>14:00</Open>
<Close>17:00</Close>
</Hours>
<Hours>
<DayOfWeek>Tuesday</DayOfWeek>
<Open>10:00</Open>
<Close>13:00</Close>
<Open>17:30</Open>
<Close>20:30</Close>
</Hours>
<Hours>
<DayOfWeek>Wednesday</DayOfWeek>
<Open>14:00</Open>
<Close>17:00</Close>
<Open>17:30</Open>
<Close>20:30</Close>
</Hours>
<Hours>
<DayOfWeek>Thursday</DayOfWeek>
<Open>14:00</Open>
<Close>17:00</Close>
<Open>17:30</Open>
<Close>20:30</Close>
</Hours>
<Hours>
<DayOfWeek>Friday</DayOfWeek>
<Open>CLOSED</Open>
<Close>CLOSED</Close>
</Hours>
<Hours>
<DayOfWeek>Saturday</DayOfWeek>
<Open>10:00</Open>
<Close>14:00</Close>
</Hours>
<Hours>
<DayOfWeek>Sunday</DayOfWeek>
<Open>CLOSED</Open>
<Close>CLOSED</Close>
</Hours>
</BranchHours>
<HolidayClosures>
<HolidayClosure>
<HolidayName>New Year's Day</HolidayName>
<HolidayDate>2017-01-01</HolidayDate>
</HolidayClosure>
<HolidayClosure>
<HolidayName>Family Day</HolidayName>
<HolidayDate>2017-02-20</HolidayDate>
</HolidayClosure>
<HolidayClosure>
<HolidayName>Good Friday</HolidayName>
<HolidayDate>2017-04-14</HolidayDate>
</HolidayClosure>
<HolidayClosure>
<HolidayName>Easter Sunday</HolidayName>
<HolidayDate>2017-04-16</HolidayDate>
</HolidayClosure>
<HolidayClosure>
<HolidayName>Easter Monday</HolidayName>
<HolidayDate>2017-04-17</HolidayDate>
</HolidayClosure>
<HolidayClosure>
<HolidayName>Victoria Day</HolidayName>
<HolidayDate>2017-05-22</HolidayDate>
</HolidayClosure>
<HolidayClosure>
<HolidayName>Canada Day</HolidayName>
<HolidayDate>2017-07-01</HolidayDate>
</HolidayClosure>
<HolidayClosure>
<HolidayName>Colonel By Day</HolidayName>
<HolidayDate>2017-08-07</HolidayDate>
</HolidayClosure>
<HolidayClosure>
<HolidayName>Labour Day</HolidayName>
<HolidayDate>2017-09-04</HolidayDate>
</HolidayClosure>
<HolidayClosure>
<HolidayName>Thanksgiving</HolidayName>
<HolidayDate>2017-10-09</HolidayDate>
</HolidayClosure>
<HolidayClosure>
<HolidayName>Remembrance Day</HolidayName>
<HolidayDate>2017-11-11</HolidayDate>
</HolidayClosure>
<HolidayClosure>
<HolidayName>Christmas Eve</HolidayName>
<HolidayDate>2017-12-24</HolidayDate>
</HolidayClosure>
<HolidayClosure>
<HolidayName>Christmas Day</HolidayName>
<HolidayDate>2017-12-25</HolidayDate>
</HolidayClosure>
<HolidayClosure>
<HolidayName>Boxing Day</HolidayName>
<HolidayDate>2017-12-26</HolidayDate>
</HolidayClosure>
<HolidayClosure>
<HolidayName>New Year's Eve</HolidayName>
<HolidayDate>2017-12-31</HolidayDate>
</HolidayClosure>
</HolidayClosures>
<Address>5630 Osgoode Main</Address>
<ZipCode>K0A 2W0</ZipCode>
<Coordinates>
<Latitude>45.14914600</Latitude>
<Longitude>-75.60248100</Longitude>
</Coordinates>
<PhoneNumber>613-580-2940</PhoneNumber>
<Email/>
</BranchInfo>
<BranchInfo>
<BranchId>RM</BranchId>
<Name>Richmond</Name>
<ShortName>Richmond</ShortName>
<ImageUrl>
http://biblioottawalibrary.ca/sites/biblioottawalibrary.ca/files/imagecache/branch_image_preview/images/branches/br_rm_ext_1_0.jpg
</ImageUrl>
<BranchHours>
<Hours>
<DayOfWeek>Monday</DayOfWeek>
<Open>13:30</Open>
<Close>17:00</Close>
<Open>18:00</Open>
<Close>20:30</Close>
</Hours>
<Hours>
<DayOfWeek>Tuesday</DayOfWeek>
<Open>10:00</Open>
<Close>12:30</Close>
<Open>13:30</Open>
<Close>17:00</Close>
<Open>18:00</Open>
<Close>20:30</Close>
</Hours>
<Hours>
<DayOfWeek>Wednesday</DayOfWeek>
<Open>13:30</Open>
<Close>17:00</Close>
<Open>18:00</Open>
<Close>20:30</Close>
</Hours>
<Hours>
<DayOfWeek>Thursday</DayOfWeek>
<Open>13:30</Open>
<Close>17:00</Close>
<Open>18:00</Open>
<Close>20:30</Close>
</Hours>
<Hours>
<DayOfWeek>Friday</DayOfWeek>
<Open>13:30</Open>
<Close>17:00</Close>
</Hours>
<Hours>
<DayOfWeek>Saturday</DayOfWeek>
<Open>10:00</Open>
<Close>14:00</Close>
</Hours>
<Hours>
<DayOfWeek>Sunday</DayOfWeek>
<Open>CLOSED</Open>
<Close>CLOSED</Close>
</Hours>
</BranchHours>
<HolidayClosures>
<HolidayClosure>
<HolidayName>New Year's Day</HolidayName>
<HolidayDate>2017-01-01</HolidayDate>
</HolidayClosure>
<HolidayClosure>
<HolidayName>Family Day</HolidayName>
<HolidayDate>2017-02-20</HolidayDate>
</HolidayClosure>
<HolidayClosure>
<HolidayName>Good Friday</HolidayName>
<HolidayDate>2017-04-14</HolidayDate>
</HolidayClosure>
<HolidayClosure>
<HolidayName>Easter Sunday</HolidayName>
<HolidayDate>2017-04-16</HolidayDate>
</HolidayClosure>
<HolidayClosure>
<HolidayName>Easter Monday</HolidayName>
<HolidayDate>2017-04-17</HolidayDate>
</HolidayClosure>
<HolidayClosure>
<HolidayName>Victoria Day</HolidayName>
<HolidayDate>2017-05-22</HolidayDate>
</HolidayClosure>
<HolidayClosure>
<HolidayName>Canada Day</HolidayName>
<HolidayDate>2017-07-01</HolidayDate>
</HolidayClosure>
<HolidayClosure>
<HolidayName>Colonel By Day</HolidayName>
<HolidayDate>2017-08-07</HolidayDate>
</HolidayClosure>
<HolidayClosure>
<HolidayName>Labour Day</HolidayName>
<HolidayDate>2017-09-04</HolidayDate>
</HolidayClosure>
<HolidayClosure>
<HolidayName>Thanksgiving</HolidayName>
<HolidayDate>2017-10-09</HolidayDate>
</HolidayClosure>
<HolidayClosure>
<HolidayName>Remembrance Day</HolidayName>
<HolidayDate>2017-11-11</HolidayDate>
</HolidayClosure>
<HolidayClosure>
<HolidayName>Christmas Eve</HolidayName>
<HolidayDate>2017-12-24</HolidayDate>
</HolidayClosure>
<HolidayClosure>
<HolidayName>Christmas Day</HolidayName>
<HolidayDate>2017-12-25</HolidayDate>
</HolidayClosure>
<HolidayClosure>
<HolidayName>Boxing Day</HolidayName>
<HolidayDate>2017-12-26</HolidayDate>
</HolidayClosure>
<HolidayClosure>
<HolidayName>New Year's Eve</HolidayName>
<HolidayDate>2017-12-31</HolidayDate>
</HolidayClosure>
</HolidayClosures>
<Address>6240 Perth Avenue</Address>
<ZipCode>K0A 2Z0</ZipCode>
<Coordinates>
<Latitude>45.19192700</Latitude>
<Longitude>-75.84422300</Longitude>
</Coordinates>
<PhoneNumber>613-580-2940</PhoneNumber>
<Email/>
</BranchInfo>
<BranchInfo>
<BranchId>RI</BranchId>
<Name>Rideau</Name>
<ShortName>Rideau</ShortName>
<ImageUrl>
http://biblioottawalibrary.ca/sites/biblioottawalibrary.ca/files/imagecache/branch_image_preview/images/branches/br_ri_ext_1.jpg
</ImageUrl>
<BranchHours>
<Hours>
<DayOfWeek>Monday</DayOfWeek>
<Open>10:00</Open>
<Close>20:30</Close>
</Hours>
<Hours>
<DayOfWeek>Tuesday</DayOfWeek>
<Open>10:00</Open>
<Close>20:30</Close>
</Hours>
<Hours>
<DayOfWeek>Wednesday</DayOfWeek>
<Open>10:00</Open>
<Close>20:30</Close>
</Hours>
<Hours>
<DayOfWeek>Thursday</DayOfWeek>
<Open>10:00</Open>
<Close>20:30</Close>
</Hours>
<Hours>
<DayOfWeek>Friday</DayOfWeek>
<Open>13:00</Open>
<Close>18:00</Close>
</Hours>
<Hours>
<DayOfWeek>Saturday</DayOfWeek>
<Open>10:00</Open>
<Close>17:00</Close>
</Hours>
<Hours>
<DayOfWeek>Sunday</DayOfWeek>
<Open>CLOSED</Open>
<Close>CLOSED</Close>
</Hours>
</BranchHours>
<HolidayClosures>
<HolidayClosure>
<HolidayName>New Year's Day</HolidayName>
<HolidayDate>2017-01-01</HolidayDate>
</HolidayClosure>
<HolidayClosure>
<HolidayName>Family Day</HolidayName>
<HolidayDate>2017-02-20</HolidayDate>
</HolidayClosure>
<HolidayClosure>
<HolidayName>Good Friday</HolidayName>
<HolidayDate>2017-04-14</HolidayDate>
</HolidayClosure>
<HolidayClosure>
<HolidayName>Easter Sunday</HolidayName>
<HolidayDate>2017-04-16</HolidayDate>
</HolidayClosure>
<HolidayClosure>
<HolidayName>Easter Monday</HolidayName>
<HolidayDate>2017-04-17</HolidayDate>
</HolidayClosure>
<HolidayClosure>
<HolidayName>Victoria Day</HolidayName>
<HolidayDate>2017-05-22</HolidayDate>
</HolidayClosure>
<HolidayClosure>
<HolidayName>Canada Day</HolidayName>
<HolidayDate>2017-07-01</HolidayDate>
</HolidayClosure>
<HolidayClosure>
<HolidayName>Colonel By Day</HolidayName>
<HolidayDate>2017-08-07</HolidayDate>
</HolidayClosure>
<HolidayClosure>
<HolidayName>Labour Day</HolidayName>
<HolidayDate>2017-09-04</HolidayDate>
</HolidayClosure>
<HolidayClosure>
<HolidayName>Thanksgiving</HolidayName>
<HolidayDate>2017-10-09</HolidayDate>
</HolidayClosure>
<HolidayClosure>
<HolidayName>Remembrance Day</HolidayName>
<HolidayDate>2017-11-11</HolidayDate>
</HolidayClosure>
<HolidayClosure>
<HolidayName>Christmas Eve</HolidayName>
<HolidayDate>2017-12-24</HolidayDate>
</HolidayClosure>
<HolidayClosure>
<HolidayName>Christmas Day</HolidayName>
<HolidayDate>2017-12-25</HolidayDate>
</HolidayClosure>
<HolidayClosure>
<HolidayName>Boxing Day</HolidayName>
<HolidayDate>2017-12-26</HolidayDate>
</HolidayClosure>
<HolidayClosure>
<HolidayName>New Year's Eve</HolidayName>
<HolidayDate>2017-12-31</HolidayDate>
</HolidayClosure>
</HolidayClosures>
<Address>377 Rideau</Address>
<ZipCode>K1N 5Y6</ZipCode>
<Coordinates>
<Latitude>45.43097000</Latitude>
<Longitude>-75.68284000</Longitude>
</Coordinates>
<PhoneNumber>613-580-2940</PhoneNumber>
<Email/>
</BranchInfo>
<BranchInfo>
<BranchId>RP</BranchId>
<Name>Rockcliffe Park</Name>
<ShortName>Rockcliffe Park</ShortName>
<ImageUrl>
http://biblioottawalibrary.ca/sites/biblioottawalibrary.ca/files/imagecache/branch_image_preview/images/branches/br_rp_ext_1_0.jpg
</ImageUrl>
<BranchHours>
<Hours>
<DayOfWeek>Monday</DayOfWeek>
<Open>10:00</Open>
<Close>17:00</Close>
</Hours>
<Hours>
<DayOfWeek>Tuesday</DayOfWeek>
<Open>13:00</Open>
<Close>20:30</Close>
</Hours>
<Hours>
<DayOfWeek>Wednesday</DayOfWeek>
<Open>10:00</Open>
<Close>17:00</Close>
</Hours>
<Hours>
<DayOfWeek>Thursday</DayOfWeek>
<Open>13:00</Open>
<Close>20:30</Close>
</Hours>
<Hours>
<DayOfWeek>Friday</DayOfWeek>
<Open>14:00</Open>
<Close>18:00</Close>
</Hours>
<Hours>
<DayOfWeek>Saturday</DayOfWeek>
<Open>10:00</Open>
<Close>14:00</Close>
</Hours>
<Hours>
<DayOfWeek>Sunday</DayOfWeek>
<Open>CLOSED</Open>
<Close>CLOSED</Close>
</Hours>
</BranchHours>
<HolidayClosures>
<HolidayClosure>
<HolidayName>New Year's Day</HolidayName>
<HolidayDate>2017-01-01</HolidayDate>
</HolidayClosure>
<HolidayClosure>
<HolidayName>Family Day</HolidayName>
<HolidayDate>2017-02-20</HolidayDate>
</HolidayClosure>
<HolidayClosure>
<HolidayName>Good Friday</HolidayName>
<HolidayDate>2017-04-14</HolidayDate>
</HolidayClosure>
<HolidayClosure>
<HolidayName>Easter Sunday</HolidayName>
<HolidayDate>2017-04-16</HolidayDate>
</HolidayClosure>
<HolidayClosure>
<HolidayName>Easter Monday</HolidayName>
<HolidayDate>2017-04-17</HolidayDate>
</HolidayClosure>
<HolidayClosure>
<HolidayName>Victoria Day</HolidayName>
<HolidayDate>2017-05-22</HolidayDate>
</HolidayClosure>
<HolidayClosure>
<HolidayName>Canada Day</HolidayName>
<HolidayDate>2017-07-01</HolidayDate>
</HolidayClosure>
<HolidayClosure>
<HolidayName>Colonel By Day</HolidayName>
<HolidayDate>2017-08-07</HolidayDate>
</HolidayClosure>
<HolidayClosure>
<HolidayName>Labour Day</HolidayName>
<HolidayDate>2017-09-04</HolidayDate>
</HolidayClosure>
<HolidayClosure>
<HolidayName>Thanksgiving</HolidayName>
<HolidayDate>2017-10-09</HolidayDate>
</HolidayClosure>
<HolidayClosure>
<HolidayName>Remembrance Day</HolidayName>
<HolidayDate>2017-11-11</HolidayDate>
</HolidayClosure>
<HolidayClosure>
<HolidayName>Christmas Eve</HolidayName>
<HolidayDate>2017-12-24</HolidayDate>
</HolidayClosure>
<HolidayClosure>
<HolidayName>Christmas Day</HolidayName>
<HolidayDate>2017-12-25</HolidayDate>
</HolidayClosure>
<HolidayClosure>
<HolidayName>Boxing Day</HolidayName>
<HolidayDate>2017-12-26</HolidayDate>
</HolidayClosure>
<HolidayClosure>
<HolidayName>New Year's Eve</HolidayName>
<HolidayDate>2017-12-31</HolidayDate>
</HolidayClosure>
</HolidayClosures>
<Address>380 Springfield</Address>
<ZipCode>K1M 0L7</ZipCode>
<Coordinates>
<Latitude>45.45183700</Latitude>
<Longitude>-75.67887100</Longitude>
</Coordinates>
<PhoneNumber>613-580-2940</PhoneNumber>
<Email/>
</BranchInfo>
<BranchInfo>
<BranchId>RO</BranchId>
<Name>Rosemount</Name>
<ShortName>Rosemount</ShortName>
<ImageUrl>
http://biblioottawalibrary.ca/sites/biblioottawalibrary.ca/files/imagecache/branch_image_preview/images/branches/br_ro_ext_1.jpg
</ImageUrl>
<BranchHours>
<Hours>
<DayOfWeek>Monday</DayOfWeek>
<Open>10:00</Open>
<Close>20:30</Close>
</Hours>
<Hours>
<DayOfWeek>Tuesday</DayOfWeek>
<Open>10:00</Open>
<Close>20:30</Close>
</Hours>
<Hours>
<DayOfWeek>Wednesday</DayOfWeek>
<Open>10:00</Open>
<Close>20:30</Close>
</Hours>
<Hours>
<DayOfWeek>Thursday</DayOfWeek>
<Open>10:00</Open>
<Close>20:30</Close>
</Hours>
<Hours>
<DayOfWeek>Friday</DayOfWeek>
<Open>13:00</Open>
<Close>18:00</Close>
</Hours>
<Hours>
<DayOfWeek>Saturday</DayOfWeek>
<Open>10:00</Open>
<Close>17:00</Close>
</Hours>
<Hours>
<DayOfWeek>Sunday</DayOfWeek>
<Open>CLOSED</Open>
<Close>CLOSED</Close>
</Hours>
</BranchHours>
<HolidayClosures>
<HolidayClosure>
<HolidayName>New Year's Day</HolidayName>
<HolidayDate>2017-01-01</HolidayDate>
</HolidayClosure>
<HolidayClosure>
<HolidayName>Family Day</HolidayName>
<HolidayDate>2017-02-20</HolidayDate>
</HolidayClosure>
<HolidayClosure>
<HolidayName>Good Friday</HolidayName>
<HolidayDate>2017-04-14</HolidayDate>
</HolidayClosure>
<HolidayClosure>
<HolidayName>Easter Sunday</HolidayName>
<HolidayDate>2017-04-16</HolidayDate>
</HolidayClosure>
<HolidayClosure>
<HolidayName>Easter Monday</HolidayName>
<HolidayDate>2017-04-17</HolidayDate>
</HolidayClosure>
<HolidayClosure>
<HolidayName>Victoria Day</HolidayName>
<HolidayDate>2017-05-22</HolidayDate>
</HolidayClosure>
<HolidayClosure>
<HolidayName>Canada Day</HolidayName>
<HolidayDate>2017-07-01</HolidayDate>
</HolidayClosure>
<HolidayClosure>
<HolidayName>Colonel By Day</HolidayName>
<HolidayDate>2017-08-07</HolidayDate>
</HolidayClosure>
<HolidayClosure>
<HolidayName>Labour Day</HolidayName>
<HolidayDate>2017-09-04</HolidayDate>
</HolidayClosure>
<HolidayClosure>
<HolidayName>Thanksgiving</HolidayName>
<HolidayDate>2017-10-09</HolidayDate>
</HolidayClosure>
<HolidayClosure>
<HolidayName>Remembrance Day</HolidayName>
<HolidayDate>2017-11-11</HolidayDate>
</HolidayClosure>
<HolidayClosure>
<HolidayName>Christmas Eve</HolidayName>
<HolidayDate>2017-12-24</HolidayDate>
</HolidayClosure>
<HolidayClosure>
<HolidayName>Christmas Day</HolidayName>
<HolidayDate>2017-12-25</HolidayDate>
</HolidayClosure>
<HolidayClosure>
<HolidayName>Boxing Day</HolidayName>
<HolidayDate>2017-12-26</HolidayDate>
</HolidayClosure>
<HolidayClosure>
<HolidayName>New Year's Eve</HolidayName>
<HolidayDate>2017-12-31</HolidayDate>
</HolidayClosure>
</HolidayClosures>
<Address>18 Rosemount</Address>
<ZipCode>K1Y 1P4</ZipCode>
<Coordinates>
<Latitude>45.40229200</Latitude>
<Longitude>-75.72586300</Longitude>
</Coordinates>
<PhoneNumber>613-580-2940</PhoneNumber>
<Email/>
</BranchInfo>
<BranchInfo>
<BranchId>RD</BranchId>
<Name>Ruth E. Dickinson</Name>
<ShortName>Ruth E. Dickinson</ShortName>
<ImageUrl>
http://biblioottawalibrary.ca/sites/biblioottawalibrary.ca/files/imagecache/branch_image_preview/images/branches/br_rd_ext_1_0.jpg
</ImageUrl>
<BranchHours>
<Hours>
<DayOfWeek>Monday</DayOfWeek>
<Open>10:00</Open>
<Close>20:30</Close>
</Hours>
<Hours>
<DayOfWeek>Tuesday</DayOfWeek>
<Open>10:00</Open>
<Close>20:30</Close>
</Hours>
<Hours>
<DayOfWeek>Wednesday</DayOfWeek>
<Open>10:00</Open>
<Close>20:30</Close>
</Hours>
<Hours>
<DayOfWeek>Thursday</DayOfWeek>
<Open>10:00</Open>
<Close>20:30</Close>
</Hours>
<Hours>
<DayOfWeek>Friday</DayOfWeek>
<Open>13:00</Open>
<Close>18:00</Close>
</Hours>
<Hours>
<DayOfWeek>Saturday</DayOfWeek>
<Open>10:00</Open>
<Close>17:00</Close>
</Hours>
<Hours>
<DayOfWeek>Sunday</DayOfWeek>
<Open>CLOSED</Open>
<Close>CLOSED</Close>
</Hours>
</BranchHours>
<HolidayClosures>
<HolidayClosure>
<HolidayName>New Year's Day</HolidayName>
<HolidayDate>2017-01-01</HolidayDate>
</HolidayClosure>
<HolidayClosure>
<HolidayName>Family Day</HolidayName>
<HolidayDate>2017-02-20</HolidayDate>
</HolidayClosure>
<HolidayClosure>
<HolidayName>Good Friday</HolidayName>
<HolidayDate>2017-04-14</HolidayDate>
</HolidayClosure>
<HolidayClosure>
<HolidayName>Easter Sunday</HolidayName>
<HolidayDate>2017-04-16</HolidayDate>
</HolidayClosure>
<HolidayClosure>
<HolidayName>Easter Monday</HolidayName>
<HolidayDate>2017-04-17</HolidayDate>
</HolidayClosure>
<HolidayClosure>
<HolidayName>Victoria Day</HolidayName>
<HolidayDate>2017-05-22</HolidayDate>
</HolidayClosure>
<HolidayClosure>
<HolidayName>Canada Day</HolidayName>
<HolidayDate>2017-07-01</HolidayDate>
</HolidayClosure>
<HolidayClosure>
<HolidayName>Colonel By Day</HolidayName>
<HolidayDate>2017-08-07</HolidayDate>
</HolidayClosure>
<HolidayClosure>
<HolidayName>Labour Day</HolidayName>
<HolidayDate>2017-09-04</HolidayDate>
</HolidayClosure>
<HolidayClosure>
<HolidayName>Thanksgiving</HolidayName>
<HolidayDate>2017-10-09</HolidayDate>
</HolidayClosure>
<HolidayClosure>
<HolidayName>Remembrance Day</HolidayName>
<HolidayDate>2017-11-11</HolidayDate>
</HolidayClosure>
<HolidayClosure>
<HolidayName>Christmas Eve</HolidayName>
<HolidayDate>2017-12-24</HolidayDate>
</HolidayClosure>
<HolidayClosure>
<HolidayName>Christmas Day</HolidayName>
<HolidayDate>2017-12-25</HolidayDate>
</HolidayClosure>
<HolidayClosure>
<HolidayName>Boxing Day</HolidayName>
<HolidayDate>2017-12-26</HolidayDate>
</HolidayClosure>
<HolidayClosure>
<HolidayName>New Year's Eve</HolidayName>
<HolidayDate>2017-12-31</HolidayDate>
</HolidayClosure>
</HolidayClosures>
<Address>100 Malvern</Address>
<ZipCode>K2J 2G5</ZipCode>
<Coordinates>
<Latitude>45.28140900</Latitude>
<Longitude>-75.75856400</Longitude>
</Coordinates>
<PhoneNumber>613-580-2940</PhoneNumber>
<Email/>
</BranchInfo>
<BranchInfo>
<BranchId>SL</BranchId>
<Name>St-Laurent</Name>
<ShortName>St-Laurent</ShortName>
<ImageUrl>
http://biblioottawalibrary.ca/sites/biblioottawalibrary.ca/files/imagecache/branch_image_preview/images/branches/br_sl_ext_1_0.jpg
</ImageUrl>
<BranchHours>
<Hours>
<DayOfWeek>Monday</DayOfWeek>
<Open>10:00</Open>
<Close>20:30</Close>
</Hours>
<Hours>
<DayOfWeek>Tuesday</DayOfWeek>
<Open>10:00</Open>
<Close>20:30</Close>
</Hours>
<Hours>
<DayOfWeek>Wednesday</DayOfWeek>
<Open>10:00</Open>
<Close>20:30</Close>
</Hours>
<Hours>
<DayOfWeek>Thursday</DayOfWeek>
<Open>10:00</Open>
<Close>20:30</Close>
</Hours>
<Hours>
<DayOfWeek>Friday</DayOfWeek>
<Open>13:00</Open>
<Close>18:00</Close>
</Hours>
<Hours>
<DayOfWeek>Saturday</DayOfWeek>
<Open>10:00</Open>
<Close>17:00</Close>
</Hours>
<Hours>
<DayOfWeek>Sunday</DayOfWeek>
<Open>CLOSED</Open>
<Close>CLOSED</Close>
</Hours>
</BranchHours>
<HolidayClosures>
<HolidayClosure>
<HolidayName>New Year's Day</HolidayName>
<HolidayDate>2017-01-01</HolidayDate>
</HolidayClosure>
<HolidayClosure>
<HolidayName>Family Day</HolidayName>
<HolidayDate>2017-02-20</HolidayDate>
</HolidayClosure>
<HolidayClosure>
<HolidayName>Good Friday</HolidayName>
<HolidayDate>2017-04-14</HolidayDate>
</HolidayClosure>
<HolidayClosure>
<HolidayName>Easter Sunday</HolidayName>
<HolidayDate>2017-04-16</HolidayDate>
</HolidayClosure>
<HolidayClosure>
<HolidayName>Easter Monday</HolidayName>
<HolidayDate>2017-04-17</HolidayDate>
</HolidayClosure>
<HolidayClosure>
<HolidayName>Victoria Day</HolidayName>
<HolidayDate>2017-05-22</HolidayDate>
</HolidayClosure>
<HolidayClosure>
<HolidayName>Canada Day</HolidayName>
<HolidayDate>2017-07-01</HolidayDate>
</HolidayClosure>
<HolidayClosure>
<HolidayName>Colonel By Day</HolidayName>
<HolidayDate>2017-08-07</HolidayDate>
</HolidayClosure>
<HolidayClosure>
<HolidayName>Labour Day</HolidayName>
<HolidayDate>2017-09-04</HolidayDate>
</HolidayClosure>
<HolidayClosure>
<HolidayName>Thanksgiving</HolidayName>
<HolidayDate>2017-10-09</HolidayDate>
</HolidayClosure>
<HolidayClosure>
<HolidayName>Remembrance Day</HolidayName>
<HolidayDate>2017-11-11</HolidayDate>
</HolidayClosure>
<HolidayClosure>
<HolidayName>Christmas Eve</HolidayName>
<HolidayDate>2017-12-24</HolidayDate>
</HolidayClosure>
<HolidayClosure>
<HolidayName>Christmas Day</HolidayName>
<HolidayDate>2017-12-25</HolidayDate>
</HolidayClosure>
<HolidayClosure>
<HolidayName>Boxing Day</HolidayName>
<HolidayDate>2017-12-26</HolidayDate>
</HolidayClosure>
<HolidayClosure>
<HolidayName>New Year's Eve</HolidayName>
<HolidayDate>2017-12-31</HolidayDate>
</HolidayClosure>
</HolidayClosures>
<Address>515 Ct</Address>
<ZipCode>K1K 0Z8</ZipCode>
<Coordinates>
<Latitude>45.43651100</Latitude>
<Longitude>-75.64679100</Longitude>
</Coordinates>
<PhoneNumber>613-580-2940</PhoneNumber>
<Email/>
</BranchInfo>
<BranchInfo>
<BranchId>ST</BranchId>
<Name>Stittsville</Name>
<ShortName>Stittsville</ShortName>
<ImageUrl>
http://biblioottawalibrary.ca/sites/biblioottawalibrary.ca/files/imagecache/branch_image_preview/images/branches/br_st_ext_2_0.jpg
</ImageUrl>
<BranchHours>
<Hours>
<DayOfWeek>Monday</DayOfWeek>
<Open>10:00</Open>
<Close>20:30</Close>
</Hours>
<Hours>
<DayOfWeek>Tuesday</DayOfWeek>
<Open>10:00</Open>
<Close>20:30</Close>
</Hours>
<Hours>
<DayOfWeek>Wednesday</DayOfWeek>
<Open>10:00</Open>
<Close>20:30</Close>
</Hours>
<Hours>
<DayOfWeek>Thursday</DayOfWeek>
<Open>10:00</Open>
<Close>20:30</Close>
</Hours>
<Hours>
<DayOfWeek>Friday</DayOfWeek>
<Open>13:00</Open>
<Close>18:00</Close>
</Hours>
<Hours>
<DayOfWeek>Saturday</DayOfWeek>
<Open>10:00</Open>
<Close>17:00</Close>
</Hours>
<Hours>
<DayOfWeek>Sunday</DayOfWeek>
<Open>CLOSED</Open>
<Close>CLOSED</Close>
</Hours>
</BranchHours>
<HolidayClosures>
<HolidayClosure>
<HolidayName>New Year's Day</HolidayName>
<HolidayDate>2017-01-01</HolidayDate>
</HolidayClosure>
<HolidayClosure>
<HolidayName>Family Day</HolidayName>
<HolidayDate>2017-02-20</HolidayDate>
</HolidayClosure>
<HolidayClosure>
<HolidayName>Good Friday</HolidayName>
<HolidayDate>2017-04-14</HolidayDate>
</HolidayClosure>
<HolidayClosure>
<HolidayName>Easter Sunday</HolidayName>
<HolidayDate>2017-04-16</HolidayDate>
</HolidayClosure>
<HolidayClosure>
<HolidayName>Easter Monday</HolidayName>
<HolidayDate>2017-04-17</HolidayDate>
</HolidayClosure>
<HolidayClosure>
<HolidayName>Victoria Day</HolidayName>
<HolidayDate>2017-05-22</HolidayDate>
</HolidayClosure>
<HolidayClosure>
<HolidayName>Canada Day</HolidayName>
<HolidayDate>2017-07-01</HolidayDate>
</HolidayClosure>
<HolidayClosure>
<HolidayName>Colonel By Day</HolidayName>
<HolidayDate>2017-08-07</HolidayDate>
</HolidayClosure>
<HolidayClosure>
<HolidayName>Labour Day</HolidayName>
<HolidayDate>2017-09-04</HolidayDate>
</HolidayClosure>
<HolidayClosure>
<HolidayName>Thanksgiving</HolidayName>
<HolidayDate>2017-10-09</HolidayDate>
</HolidayClosure>
<HolidayClosure>
<HolidayName>Remembrance Day</HolidayName>
<HolidayDate>2017-11-11</HolidayDate>
</HolidayClosure>
<HolidayClosure>
<HolidayName>Christmas Eve</HolidayName>
<HolidayDate>2017-12-24</HolidayDate>
</HolidayClosure>
<HolidayClosure>
<HolidayName>Christmas Day</HolidayName>
<HolidayDate>2017-12-25</HolidayDate>
</HolidayClosure>
<HolidayClosure>
<HolidayName>Boxing Day</HolidayName>
<HolidayDate>2017-12-26</HolidayDate>
</HolidayClosure>
<HolidayClosure>
<HolidayName>New Year's Eve</HolidayName>
<HolidayDate>2017-12-31</HolidayDate>
</HolidayClosure>
</HolidayClosures>
<Address>1637 Stittsville Main</Address>
<ZipCode>K2S 1A9</ZipCode>
<Coordinates>
<Latitude>45.25507200</Latitude>
<Longitude>-75.91550600</Longitude>
</Coordinates>
<PhoneNumber>613-580-2940</PhoneNumber>
<Email/>
</BranchInfo>
<BranchInfo>
<BranchId>SU</BranchId>
<Name>Sunnyside</Name>
<ShortName>Sunnyside</ShortName>
<ImageUrl>
http://biblioottawalibrary.ca/sites/biblioottawalibrary.ca/files/imagecache/branch_image_preview/images/branches/br_su_ext_2.jpg
</ImageUrl>
<BranchHours>
<Hours>
<DayOfWeek>Monday</DayOfWeek>
<Open>10:00</Open>
<Close>20:30</Close>
</Hours>
<Hours>
<DayOfWeek>Tuesday</DayOfWeek>
<Open>10:00</Open>
<Close>20:30</Close>
</Hours>
<Hours>
<DayOfWeek>Wednesday</DayOfWeek>
<Open>10:00</Open>
<Close>20:30</Close>
</Hours>
<Hours>
<DayOfWeek>Thursday</DayOfWeek>
<Open>10:00</Open>
<Close>20:30</Close>
</Hours>
<Hours>
<DayOfWeek>Friday</DayOfWeek>
<Open>13:00</Open>
<Close>18:00</Close>
</Hours>
<Hours>
<DayOfWeek>Saturday</DayOfWeek>
<Open>10:00</Open>
<Close>17:00</Close>
</Hours>
<Hours>
<DayOfWeek>Sunday</DayOfWeek>
<Open>CLOSED</Open>
<Close>CLOSED</Close>
</Hours>
</BranchHours>
<HolidayClosures>
<HolidayClosure>
<HolidayName>New Year's Day</HolidayName>
<HolidayDate>2017-01-01</HolidayDate>
</HolidayClosure>
<HolidayClosure>
<HolidayName>Family Day</HolidayName>
<HolidayDate>2017-02-20</HolidayDate>
</HolidayClosure>
<HolidayClosure>
<HolidayName>Good Friday</HolidayName>
<HolidayDate>2017-04-14</HolidayDate>
</HolidayClosure>
<HolidayClosure>
<HolidayName>Easter Sunday</HolidayName>
<HolidayDate>2017-04-16</HolidayDate>
</HolidayClosure>
<HolidayClosure>
<HolidayName>Easter Monday</HolidayName>
<HolidayDate>2017-04-17</HolidayDate>
</HolidayClosure>
<HolidayClosure>
<HolidayName>Victoria Day</HolidayName>
<HolidayDate>2017-05-22</HolidayDate>
</HolidayClosure>
<HolidayClosure>
<HolidayName>Canada Day</HolidayName>
<HolidayDate>2017-07-01</HolidayDate>
</HolidayClosure>
<HolidayClosure>
<HolidayName>Colonel By Day</HolidayName>
<HolidayDate>2017-08-07</HolidayDate>
</HolidayClosure>
<HolidayClosure>
<HolidayName>Labour Day</HolidayName>
<HolidayDate>2017-09-04</HolidayDate>
</HolidayClosure>
<HolidayClosure>
<HolidayName>Thanksgiving</HolidayName>
<HolidayDate>2017-10-09</HolidayDate>
</HolidayClosure>
<HolidayClosure>
<HolidayName>Remembrance Day</HolidayName>
<HolidayDate>2017-11-11</HolidayDate>
</HolidayClosure>
<HolidayClosure>
<HolidayName>Christmas Eve</HolidayName>
<HolidayDate>2017-12-24</HolidayDate>
</HolidayClosure>
<HolidayClosure>
<HolidayName>Christmas Day</HolidayName>
<HolidayDate>2017-12-25</HolidayDate>
</HolidayClosure>
<HolidayClosure>
<HolidayName>Boxing Day</HolidayName>
<HolidayDate>2017-12-26</HolidayDate>
</HolidayClosure>
<HolidayClosure>
<HolidayName>New Year's Eve</HolidayName>
<HolidayDate>2017-12-31</HolidayDate>
</HolidayClosure>
</HolidayClosures>
<Address>1049 Bank</Address>
<ZipCode>K1S 3W9</ZipCode>
<Coordinates>
<Latitude>45.39655200</Latitude>
<Longitude>-75.68410600</Longitude>
</Coordinates>
<PhoneNumber>613-580-2940</PhoneNumber>
<Email/>
</BranchInfo>
<BranchInfo>
<BranchId>VA</BranchId>
<Name>Vanier</Name>
<ShortName>Vanier</ShortName>
<ImageUrl>
http://biblioottawalibrary.ca/sites/biblioottawalibrary.ca/files/imagecache/branch_image_preview/images/branches/br_va_ext_2_0.jpg
</ImageUrl>
<BranchHours>
<Hours>
<DayOfWeek>Monday</DayOfWeek>
<Open>10:00</Open>
<Close>20:30</Close>
</Hours>
<Hours>
<DayOfWeek>Tuesday</DayOfWeek>
<Open>10:00</Open>
<Close>20:30</Close>
</Hours>
<Hours>
<DayOfWeek>Wednesday</DayOfWeek>
<Open>10:00</Open>
<Close>20:30</Close>
</Hours>
<Hours>
<DayOfWeek>Thursday</DayOfWeek>
<Open>13:00</Open>
<Close>18:00</Close>
</Hours>
<Hours>
<DayOfWeek>Friday</DayOfWeek>
<Open>13:00</Open>
<Close>18:00</Close>
</Hours>
<Hours>
<DayOfWeek>Saturday</DayOfWeek>
<Open>10:00</Open>
<Close>17:00</Close>
</Hours>
<Hours>
<DayOfWeek>Sunday</DayOfWeek>
<Open>CLOSED</Open>
<Close>CLOSED</Close>
</Hours>
</BranchHours>
<HolidayClosures>
<HolidayClosure>
<HolidayName>New Year's Day</HolidayName>
<HolidayDate>2017-01-01</HolidayDate>
</HolidayClosure>
<HolidayClosure>
<HolidayName>Family Day</HolidayName>
<HolidayDate>2017-02-20</HolidayDate>
</HolidayClosure>
<HolidayClosure>
<HolidayName>Good Friday</HolidayName>
<HolidayDate>2017-04-14</HolidayDate>
</HolidayClosure>
<HolidayClosure>
<HolidayName>Easter Sunday</HolidayName>
<HolidayDate>2017-04-16</HolidayDate>
</HolidayClosure>
<HolidayClosure>
<HolidayName>Easter Monday</HolidayName>
<HolidayDate>2017-04-17</HolidayDate>
</HolidayClosure>
<HolidayClosure>
<HolidayName>Victoria Day</HolidayName>
<HolidayDate>2017-05-22</HolidayDate>
</HolidayClosure>
<HolidayClosure>
<HolidayName>Canada Day</HolidayName>
<HolidayDate>2017-07-01</HolidayDate>
</HolidayClosure>
<HolidayClosure>
<HolidayName>Colonel By Day</HolidayName>
<HolidayDate>2017-08-07</HolidayDate>
</HolidayClosure>
<HolidayClosure>
<HolidayName>Labour Day</HolidayName>
<HolidayDate>2017-09-04</HolidayDate>
</HolidayClosure>
<HolidayClosure>
<HolidayName>Thanksgiving</HolidayName>
<HolidayDate>2017-10-09</HolidayDate>
</HolidayClosure>
<HolidayClosure>
<HolidayName>Remembrance Day</HolidayName>
<HolidayDate>2017-11-11</HolidayDate>
</HolidayClosure>
<HolidayClosure>
<HolidayName>Christmas Eve</HolidayName>
<HolidayDate>2017-12-24</HolidayDate>
</HolidayClosure>
<HolidayClosure>
<HolidayName>Christmas Day</HolidayName>
<HolidayDate>2017-12-25</HolidayDate>
</HolidayClosure>
<HolidayClosure>
<HolidayName>Boxing Day</HolidayName>
<HolidayDate>2017-12-26</HolidayDate>
</HolidayClosure>
<HolidayClosure>
<HolidayName>New Year's Eve</HolidayName>
<HolidayDate>2017-12-31</HolidayDate>
</HolidayClosure>
</HolidayClosures>
<Address>310 Pres Blancs</Address>
<ZipCode>K1L 7L5</ZipCode>
<Coordinates>
<Latitude>45.44503300</Latitude>
<Longitude>-75.66016000</Longitude>
</Coordinates>
<PhoneNumber>613-580-2940</PhoneNumber>
<Email/>
</BranchInfo>
<BranchInfo>
<BranchId>VE</BranchId>
<Name>Vernon</Name>
<ShortName>Vernon</ShortName>
<ImageUrl>
http://biblioottawalibrary.ca/sites/biblioottawalibrary.ca/files/imagecache/branch_image_preview/images/branches/br_ve_ext_1.jpg
</ImageUrl>
<BranchHours>
<Hours>
<DayOfWeek>Monday</DayOfWeek>
<Open>CLOSED</Open>
<Close>CLOSED</Close>
</Hours>
<Hours>
<DayOfWeek>Tuesday</DayOfWeek>
<Open>10:00</Open>
<Close>13:00</Close>
<Open>17:30</Open>
<Close>20:30</Close>
</Hours>
<Hours>
<DayOfWeek>Wednesday</DayOfWeek>
<Open>15:00</Open>
<Close>20:30</Close>
</Hours>
<Hours>
<DayOfWeek>Thursday</DayOfWeek>
<Open>17:30</Open>
<Close>20:30</Close>
</Hours>
<Hours>
<DayOfWeek>Friday</DayOfWeek>
<Open>CLOSED</Open>
<Close>CLOSED</Close>
</Hours>
<Hours>
<DayOfWeek>Saturday</DayOfWeek>
<Open>10:00</Open>
<Close>14:00</Close>
</Hours>
<Hours>
<DayOfWeek>Sunday</DayOfWeek>
<Open>CLOSED</Open>
<Close>CLOSED</Close>
</Hours>
</BranchHours>
<HolidayClosures>
<HolidayClosure>
<HolidayName>New Year's Day</HolidayName>
<HolidayDate>2017-01-01</HolidayDate>
</HolidayClosure>
<HolidayClosure>
<HolidayName>Family Day</HolidayName>
<HolidayDate>2017-02-20</HolidayDate>
</HolidayClosure>
<HolidayClosure>
<HolidayName>Good Friday</HolidayName>
<HolidayDate>2017-04-14</HolidayDate>
</HolidayClosure>
<HolidayClosure>
<HolidayName>Easter Sunday</HolidayName>
<HolidayDate>2017-04-16</HolidayDate>
</HolidayClosure>
<HolidayClosure>
<HolidayName>Easter Monday</HolidayName>
<HolidayDate>2017-04-17</HolidayDate>
</HolidayClosure>
<HolidayClosure>
<HolidayName>Victoria Day</HolidayName>
<HolidayDate>2017-05-22</HolidayDate>
</HolidayClosure>
<HolidayClosure>
<HolidayName>Canada Day</HolidayName>
<HolidayDate>2017-07-01</HolidayDate>
</HolidayClosure>
<HolidayClosure>
<HolidayName>Colonel By Day</HolidayName>
<HolidayDate>2017-08-07</HolidayDate>
</HolidayClosure>
<HolidayClosure>
<HolidayName>Labour Day</HolidayName>
<HolidayDate>2017-09-04</HolidayDate>
</HolidayClosure>
<HolidayClosure>
<HolidayName>Thanksgiving</HolidayName>
<HolidayDate>2017-10-09</HolidayDate>
</HolidayClosure>
<HolidayClosure>
<HolidayName>Remembrance Day</HolidayName>
<HolidayDate>2017-11-11</HolidayDate>
</HolidayClosure>
<HolidayClosure>
<HolidayName>Christmas Eve</HolidayName>
<HolidayDate>2017-12-24</HolidayDate>
</HolidayClosure>
<HolidayClosure>
<HolidayName>Christmas Day</HolidayName>
<HolidayDate>2017-12-25</HolidayDate>
</HolidayClosure>
<HolidayClosure>
<HolidayName>Boxing Day</HolidayName>
<HolidayDate>2017-12-26</HolidayDate>
</HolidayClosure>
<HolidayClosure>
<HolidayName>New Year's Eve</HolidayName>
<HolidayDate>2017-12-31</HolidayDate>
</HolidayClosure>
</HolidayClosures>
<Address>8682 Bank</Address>
<ZipCode>K0A 3J0</ZipCode>
<Coordinates>
<Latitude>45.16476200</Latitude>
<Longitude>-75.46341400</Longitude>
</Coordinates>
<PhoneNumber>613-580-2940</PhoneNumber>
<Email/>
</BranchInfo>
<BranchInfo>
<BranchId>ZBO</BranchId>
<Name>Bookmobile</Name>
<ShortName>Bookmobile</ShortName>
<ImageUrl>
http://biblioottawalibrary.ca/sites/default/files/images/images/Bookmobile1.jpg
</ImageUrl>
<BranchHours>
<Hours>
<DayOfWeek>Monday</DayOfWeek>
<Open/>
<Close/>
</Hours>
<Hours>
<DayOfWeek>Tuesday</DayOfWeek>
<Open/>
<Close/>
</Hours>
<Hours>
<DayOfWeek/>
<Open/>
<Close/>
</Hours>
<Hours>
<DayOfWeek>Thursday</DayOfWeek>
<Open/>
<Close/>
</Hours>
<Hours>
<DayOfWeek>Friday</DayOfWeek>
<Open/>
<Close/>
</Hours>
<Hours>
<DayOfWeek>Saturday</DayOfWeek>
<Open/>
<Close/>
</Hours>
<Hours>
<DayOfWeek>Sunday</DayOfWeek>
<Open/>
<Close/>
</Hours>
</BranchHours>
<HolidayClosures>
<HolidayClosure>
<HolidayName>New Year's Day</HolidayName>
<HolidayDate>2017-01-01</HolidayDate>
</HolidayClosure>
<HolidayClosure>
<HolidayName>Family Day</HolidayName>
<HolidayDate>2017-02-20</HolidayDate>
</HolidayClosure>
<HolidayClosure>
<HolidayName>Good Friday</HolidayName>
<HolidayDate>2017-04-14</HolidayDate>
</HolidayClosure>
<HolidayClosure>
<HolidayName>Easter Sunday</HolidayName>
<HolidayDate>2017-04-16</HolidayDate>
</HolidayClosure>
<HolidayClosure>
<HolidayName>Easter Monday</HolidayName>
<HolidayDate>2017-04-17</HolidayDate>
</HolidayClosure>
<HolidayClosure>
<HolidayName>Victoria Day</HolidayName>
<HolidayDate>2017-05-22</HolidayDate>
</HolidayClosure>
<HolidayClosure>
<HolidayName>Canada Day</HolidayName>
<HolidayDate>2017-07-01</HolidayDate>
</HolidayClosure>
<HolidayClosure>
<HolidayName>Colonel By Day</HolidayName>
<HolidayDate>2017-08-07</HolidayDate>
</HolidayClosure>
<HolidayClosure>
<HolidayName>Labour Day</HolidayName>
<HolidayDate>2017-09-04</HolidayDate>
</HolidayClosure>
<HolidayClosure>
<HolidayName>Thanksgiving</HolidayName>
<HolidayDate>2017-10-09</HolidayDate>
</HolidayClosure>
<HolidayClosure>
<HolidayName>Remembrance Day</HolidayName>
<HolidayDate>2017-11-11</HolidayDate>
</HolidayClosure>
<HolidayClosure>
<HolidayName>Christmas Eve</HolidayName>
<HolidayDate>2017-12-24</HolidayDate>
</HolidayClosure>
<HolidayClosure>
<HolidayName>Christmas Day</HolidayName>
<HolidayDate>2017-12-25</HolidayDate>
</HolidayClosure>
<HolidayClosure>
<HolidayName>Boxing Day</HolidayName>
<HolidayDate>2017-12-26</HolidayDate>
</HolidayClosure>
<HolidayClosure>
<HolidayName>New Year's Eve</HolidayName>
<HolidayDate>2017-12-31</HolidayDate>
</HolidayClosure>
</HolidayClosures>
<Address/>
<ZipCode/>
<Coordinates>
<Latitude>45.36387600</Latitude>
<Longitude>-75.63468900</Longitude>
</Coordinates>
<PhoneNumber>613-580-2940</PhoneNumber>
<Email>Bookmobile@BiblioOttawaLibrary.ca</Email>
</BranchInfo>
</BranchesInfo>
